[
    {
        "%vlocity_namespace%__DomainObjectAPIName__c": "json",
        "%vlocity_namespace%__DomainObjectCreationOrder__c": 0,
        "%vlocity_namespace%__DomainObjectFieldAPIName__c": "ConsumoCliente",
        "%vlocity_namespace%__FilterGroup__c": 0,
        "%vlocity_namespace%__FilterOperator__c": "=",
        "%vlocity_namespace%__FilterValue__c": "Sector",
        "%vlocity_namespace%__InterfaceFieldAPIName__c": "Sector__c",
        "%vlocity_namespace%__InterfaceObjectLookupOrder__c": 1,
        "%vlocity_namespace%__InterfaceObjectName__c": "OSFMX_ConsumosSector__c",
        "%vlocity_namespace%__IsDisabled__c": false,
        "%vlocity_namespace%__IsRequiredForUpsert__c": false,
        "%vlocity_namespace%__MapId__c": "OSFMX-ConsumoSectorCustoma1Yc0000003MclZEASItem0",
        "%vlocity_namespace%__OMplusSyncEnabled__c": false,
        "%vlocity_namespace%__UpsertKey__c": false,
        "CurrencyIsoCode": "MXN",
        "Name": "OSFMX-ConsumoSector",
        "VlocityDataPackType": "SObject",
        "VlocityRecordSObjectType": "%vlocity_namespace%__DRMapItem__c"
    },
    {
        "%vlocity_namespace%__DomainObjectAPIName__c": "json",
        "%vlocity_namespace%__DomainObjectCreationOrder__c": 1,
        "%vlocity_namespace%__DomainObjectFieldAPIName__c": "Id",
        "%vlocity_namespace%__InterfaceFieldAPIName__c": "ConsumoCliente:Id",
        "%vlocity_namespace%__IsDisabled__c": false,
        "%vlocity_namespace%__IsRequiredForUpsert__c": false,
        "%vlocity_namespace%__MapId__c": "OSFMX-ConsumoSectorCustoma1Yc0000003MclZEASItem1",
        "%vlocity_namespace%__OMplusSyncEnabled__c": false,
        "%vlocity_namespace%__UpsertKey__c": false,
        "CurrencyIsoCode": "MXN",
        "Name": "OSFMX-ConsumoSector",
        "VlocityDataPackType": "SObject",
        "VlocityRecordSObjectType": "%vlocity_namespace%__DRMapItem__c"
    },
    {
        "%vlocity_namespace%__DomainObjectAPIName__c": "json",
        "%vlocity_namespace%__DomainObjectCreationOrder__c": 1,
        "%vlocity_namespace%__DomainObjectFieldAPIName__c": "RazonSocial",
        "%vlocity_namespace%__InterfaceFieldAPIName__c": "ConsumoCliente:Razon_Social__c",
        "%vlocity_namespace%__IsDisabled__c": false,
        "%vlocity_namespace%__IsRequiredForUpsert__c": false,
        "%vlocity_namespace%__MapId__c": "OSFMX-ConsumoSectorCustoma1Yc0000003MclZEASItem2",
        "%vlocity_namespace%__OMplusSyncEnabled__c": false,
        "%vlocity_namespace%__UpsertKey__c": false,
        "CurrencyIsoCode": "MXN",
        "Name": "OSFMX-ConsumoSector",
        "VlocityDataPackType": "SObject",
        "VlocityRecordSObjectType": "%vlocity_namespace%__DRMapItem__c"
    },
    {
        "%vlocity_namespace%__DomainObjectAPIName__c": "json",
        "%vlocity_namespace%__DomainObjectCreationOrder__c": 1,
        "%vlocity_namespace%__DomainObjectFieldAPIName__c": "Volatilidad",
        "%vlocity_namespace%__InterfaceFieldAPIName__c": "ConsumoCliente:Volatibilidad__c",
        "%vlocity_namespace%__IsDisabled__c": false,
        "%vlocity_namespace%__IsRequiredForUpsert__c": false,
        "%vlocity_namespace%__MapId__c": "OSFMX-ConsumoSectorCustoma1Yc0000003MclZEASItem3",
        "%vlocity_namespace%__OMplusSyncEnabled__c": false,
        "%vlocity_namespace%__UpsertKey__c": false,
        "CurrencyIsoCode": "MXN",
        "Name": "OSFMX-ConsumoSector",
        "VlocityDataPackType": "SObject",
        "VlocityRecordSObjectType": "%vlocity_namespace%__DRMapItem__c"
    }
]