{
    "Body": "File_Sin-ofertaVinculante-png.png",
    "BodyLength": 31648,
    "ContentType": "image/png",
    "Description": "",
    "DeveloperName": "CACBAEDAA78759f1922e44b7cb756a6d920c3f503",
    "IsBodySearchable": false,
    "IsInternalUseOnly": false,
    "IsPublic": true,
    "Keywords": "",
    "Name": "Sin ofertaVinculante.png",
    "Type": "png",
    "Url": "",
    "VlocityDataPackType": "SObject",
    "VlocityRecordSObjectType": "Document",
    "VlocityRecordSourceKey": "Document/CACBAEDAA78759f1922e44b7cb756a6d920c3f503"
}