{
    "%vlocity_namespace%__Active__c": false,
    "%vlocity_namespace%__OmniScriptId__c": {
        "Name": "CreateCuadrante",
        "VlocityDataPackType": "VlocityMatchingKeyObject",
        "VlocityMatchingRecordSourceKey": "%vlocity_namespace%__OmniScript__c/OSFMX/CreateCuadrante/Procedure",
        "VlocityRecordSObjectType": "%vlocity_namespace%__OmniScript__c"
    },
    "%vlocity_namespace%__PropertySet__c": {
        "actionMessage": "",
        "chainOnStep": false,
        "disOnTplt": false,
        "elementValueMap": {
            "Cuadrante": "=IF(%OSFMX-ConsumoCliente%<>\"\",%SetCuadrantes:CuadranteCliente%,IF(%OSFMX-ConsumoSector%<>\"\",%SetCuadrantes:CuadranteSector%,%SetCuadrantes:CuadranteUlt%))"
        },
        "executionConditionalFormula": "",
        "failOnStepError": true,
        "failureConditionalFormula": "",
        "label": "SetValues10",
        "responseJSONNode": "",
        "responseJSONPath": "",
        "show": null
    },
    "%vlocity_namespace%__ReusableOmniScript__c": false,
    "%vlocity_namespace%__Type__c": "Set Values",
    "CurrencyIsoCode": "MXN",
    "Name": "SetCuadrante-OFFbyManualVolatilidad",
    "VlocityDataPackType": "SObject",
    "VlocityRecordSObjectType": "%vlocity_namespace%__Element__c",
    "VlocityRecordSourceKey": "%vlocity_namespace%__Element__c/%vlocity_namespace%__OmniScript__c/OSFMX/CreateCuadrante/Procedure/SetCuadrante-OFFbyManualVolatilidad"
}