[
    {
        "%vlocity_namespace%__DomainObjectAPIName__c": "json",
        "%vlocity_namespace%__DomainObjectCreationOrder__c": 0,
        "%vlocity_namespace%__DomainObjectFieldAPIName__c": "Contact",
        "%vlocity_namespace%__FilterGroup__c": 0,
        "%vlocity_namespace%__FilterOperator__c": "=",
        "%vlocity_namespace%__FilterValue__c": "Email",
        "%vlocity_namespace%__InterfaceFieldAPIName__c": "Email",
        "%vlocity_namespace%__InterfaceObjectLookupOrder__c": 1,
        "%vlocity_namespace%__InterfaceObjectName__c": "Contact",
        "%vlocity_namespace%__IsDisabled__c": false,
        "%vlocity_namespace%__IsRequiredForUpsert__c": false,
        "%vlocity_namespace%__MapId__c": "DRGetContactEmailCustom5593",
        "%vlocity_namespace%__OMplusSyncEnabled__c": false,
        "%vlocity_namespace%__UpsertKey__c": false,
        "CurrencyIsoCode": "MXN",
        "Name": "DRGetContactEmail",
        "VlocityDataPackType": "SObject",
        "VlocityRecordSObjectType": "%vlocity_namespace%__DRMapItem__c"
    },
    {
        "%vlocity_namespace%__DomainObjectAPIName__c": "Formula",
        "%vlocity_namespace%__DomainObjectCreationOrder__c": 0,
        "%vlocity_namespace%__DomainObjectFieldAPIName__c": "Formula",
        "%vlocity_namespace%__FormulaOrder__c": 1,
        "%vlocity_namespace%__FormulaResultPath__c": "ExistingEmail",
        "%vlocity_namespace%__Formula__c": "IF(Contact:Email, true,false)",
        "%vlocity_namespace%__IsDisabled__c": false,
        "%vlocity_namespace%__IsRequiredForUpsert__c": false,
        "%vlocity_namespace%__MapId__c": "DRGetContactEmailCustom2303",
        "%vlocity_namespace%__OMplusSyncEnabled__c": false,
        "%vlocity_namespace%__UpsertKey__c": false,
        "CurrencyIsoCode": "MXN",
        "Name": "DRGetContactEmail",
        "VlocityDataPackType": "SObject",
        "VlocityRecordSObjectType": "%vlocity_namespace%__DRMapItem__c"
    },
    {
        "%vlocity_namespace%__DomainObjectAPIName__c": "json",
        "%vlocity_namespace%__DomainObjectCreationOrder__c": 1,
        "%vlocity_namespace%__DomainObjectFieldAPIName__c": "DuplicateAccount",
        "%vlocity_namespace%__InterfaceFieldAPIName__c": "Contact:Account.Name",
        "%vlocity_namespace%__IsDisabled__c": false,
        "%vlocity_namespace%__IsRequiredForUpsert__c": false,
        "%vlocity_namespace%__MapId__c": "DRGetContactEmailCustom2197",
        "%vlocity_namespace%__OMplusSyncEnabled__c": true,
        "%vlocity_namespace%__UpsertKey__c": false,
        "CurrencyIsoCode": "MXN",
        "Name": "DRGetContactEmail",
        "VlocityDataPackType": "SObject",
        "VlocityRecordSObjectType": "%vlocity_namespace%__DRMapItem__c"
    },
    {
        "%vlocity_namespace%__DomainObjectAPIName__c": "json",
        "%vlocity_namespace%__DomainObjectCreationOrder__c": 1,
        "%vlocity_namespace%__DomainObjectFieldAPIName__c": "DuplicateEmail",
        "%vlocity_namespace%__InterfaceFieldAPIName__c": "Contact:Email",
        "%vlocity_namespace%__IsDisabled__c": false,
        "%vlocity_namespace%__IsRequiredForUpsert__c": false,
        "%vlocity_namespace%__MapId__c": "DRGetContactEmailCustom6561",
        "%vlocity_namespace%__OMplusSyncEnabled__c": true,
        "%vlocity_namespace%__UpsertKey__c": false,
        "CurrencyIsoCode": "MXN",
        "Name": "DRGetContactEmail",
        "VlocityDataPackType": "SObject",
        "VlocityRecordSObjectType": "%vlocity_namespace%__DRMapItem__c"
    },
    {
        "%vlocity_namespace%__DomainObjectAPIName__c": "json",
        "%vlocity_namespace%__DomainObjectCreationOrder__c": 1,
        "%vlocity_namespace%__DomainObjectFieldAPIName__c": "DuplicateName",
        "%vlocity_namespace%__InterfaceFieldAPIName__c": "Contact:Name",
        "%vlocity_namespace%__IsDisabled__c": false,
        "%vlocity_namespace%__IsRequiredForUpsert__c": false,
        "%vlocity_namespace%__MapId__c": "DRGetContactEmailCustom1170",
        "%vlocity_namespace%__OMplusSyncEnabled__c": true,
        "%vlocity_namespace%__UpsertKey__c": false,
        "CurrencyIsoCode": "MXN",
        "Name": "DRGetContactEmail",
        "VlocityDataPackType": "SObject",
        "VlocityRecordSObjectType": "%vlocity_namespace%__DRMapItem__c"
    },
    {
        "%vlocity_namespace%__DomainObjectAPIName__c": "json",
        "%vlocity_namespace%__DomainObjectCreationOrder__c": 1,
        "%vlocity_namespace%__DomainObjectFieldAPIName__c": "DuplicateOwner",
        "%vlocity_namespace%__InterfaceFieldAPIName__c": "Contact:Owner.Name",
        "%vlocity_namespace%__IsDisabled__c": false,
        "%vlocity_namespace%__IsRequiredForUpsert__c": false,
        "%vlocity_namespace%__MapId__c": "DRGetContactEmailCustom4776",
        "%vlocity_namespace%__OMplusSyncEnabled__c": true,
        "%vlocity_namespace%__UpsertKey__c": false,
        "CurrencyIsoCode": "MXN",
        "Name": "DRGetContactEmail",
        "VlocityDataPackType": "SObject",
        "VlocityRecordSObjectType": "%vlocity_namespace%__DRMapItem__c"
    },
    {
        "%vlocity_namespace%__DomainObjectAPIName__c": "json",
        "%vlocity_namespace%__DomainObjectCreationOrder__c": 1,
        "%vlocity_namespace%__DomainObjectFieldAPIName__c": "EEmail",
        "%vlocity_namespace%__InterfaceFieldAPIName__c": "ExistingEmail",
        "%vlocity_namespace%__IsDisabled__c": false,
        "%vlocity_namespace%__IsRequiredForUpsert__c": false,
        "%vlocity_namespace%__MapId__c": "DRGetContactEmailCustom6693",
        "%vlocity_namespace%__OMplusSyncEnabled__c": false,
        "%vlocity_namespace%__UpsertKey__c": false,
        "CurrencyIsoCode": "MXN",
        "Name": "DRGetContactEmail",
        "VlocityDataPackType": "SObject",
        "VlocityRecordSObjectType": "%vlocity_namespace%__DRMapItem__c"
    }
]