[
    {
        "%vlocity_namespace%__DomainObjectAPIName__c": "Formula",
        "%vlocity_namespace%__DomainObjectCreationOrder__c": 0,
        "%vlocity_namespace%__DomainObjectFieldAPIName__c": "Formula",
        "%vlocity_namespace%__FormulaOrder__c": 1,
        "%vlocity_namespace%__IsDisabled__c": false,
        "%vlocity_namespace%__IsRequiredForUpsert__c": false,
        "%vlocity_namespace%__MapId__c": "DRPostUpdateQuoteTransportInformationCustom543",
        "%vlocity_namespace%__UpsertKey__c": false,
        "CurrencyIsoCode": "MXN",
        "Name": "DRPostUpdateQuoteTransportInformation",
        "VlocityDataPackType": "SObject",
        "VlocityRecordSObjectType": "%vlocity_namespace%__DRMapItem__c"
    },
    {
        "%vlocity_namespace%__DomainObjectAPIName__c": "Quote",
        "%vlocity_namespace%__DomainObjectCreationOrder__c": 1,
        "%vlocity_namespace%__DomainObjectFieldAPIName__c": "Id",
        "%vlocity_namespace%__InterfaceFieldAPIName__c": "ContextId",
        "%vlocity_namespace%__IsDisabled__c": false,
        "%vlocity_namespace%__IsRequiredForUpsert__c": false,
        "%vlocity_namespace%__MapId__c": "DRPostUpdateQuoteTransportInformationCustom6975",
        "%vlocity_namespace%__UpsertKey__c": true,
        "CurrencyIsoCode": "MXN",
        "Name": "DRPostUpdateQuoteTransportInformation",
        "VlocityDataPackType": "SObject",
        "VlocityRecordSObjectType": "%vlocity_namespace%__DRMapItem__c"
    },
    {
        "%vlocity_namespace%__ConfigurationValue__c": "FAKEMAPPING",
        "%vlocity_namespace%__DomainObjectAPIName__c": "Quote",
        "%vlocity_namespace%__DomainObjectCreationOrder__c": 1,
        "%vlocity_namespace%__DomainObjectFieldAPIName__c": "Id",
        "%vlocity_namespace%__FilterOperator__c": "=",
        "%vlocity_namespace%__IsDisabled__c": true,
        "%vlocity_namespace%__IsRequiredForUpsert__c": false,
        "%vlocity_namespace%__MapId__c": "DRPostUpdateQuoteTransportInformationCustom6276",
        "%vlocity_namespace%__UpsertKey__c": false,
        "CurrencyIsoCode": "MXN",
        "Name": "DRPostUpdateQuoteTransportInformation",
        "VlocityDataPackType": "SObject",
        "VlocityRecordSObjectType": "%vlocity_namespace%__DRMapItem__c"
    },
    {
        "%vlocity_namespace%__DomainObjectAPIName__c": "Quote",
        "%vlocity_namespace%__DomainObjectCreationOrder__c": 1,
        "%vlocity_namespace%__DomainObjectFieldAPIName__c": "OSFMX_GasTransportObservation__c",
        "%vlocity_namespace%__InterfaceFieldAPIName__c": "StepComments:OSFMX_GasTransportObservation__c",
        "%vlocity_namespace%__IsDisabled__c": false,
        "%vlocity_namespace%__IsRequiredForUpsert__c": false,
        "%vlocity_namespace%__MapId__c": "DRPostUpdateQuoteTransportInformationCustom2235",
        "%vlocity_namespace%__UpsertKey__c": false,
        "CurrencyIsoCode": "MXN",
        "Name": "DRPostUpdateQuoteTransportInformation",
        "VlocityDataPackType": "SObject",
        "VlocityRecordSObjectType": "%vlocity_namespace%__DRMapItem__c"
    },
    {
        "%vlocity_namespace%__DomainObjectAPIName__c": "Quote",
        "%vlocity_namespace%__DomainObjectCreationOrder__c": 1,
        "%vlocity_namespace%__DomainObjectFieldAPIName__c": "OSFMX_GasTransportPrice__c",
        "%vlocity_namespace%__InterfaceFieldAPIName__c": "StepComments:OSFMX_GasTransportPrice__c",
        "%vlocity_namespace%__IsDisabled__c": false,
        "%vlocity_namespace%__IsRequiredForUpsert__c": false,
        "%vlocity_namespace%__MapId__c": "DRPostUpdateQuoteTransportInformationCustom9592",
        "%vlocity_namespace%__UpsertKey__c": false,
        "CurrencyIsoCode": "MXN",
        "Name": "DRPostUpdateQuoteTransportInformation",
        "VlocityDataPackType": "SObject",
        "VlocityRecordSObjectType": "%vlocity_namespace%__DRMapItem__c"
    },
    {
        "%vlocity_namespace%__DomainObjectAPIName__c": "Quote",
        "%vlocity_namespace%__DomainObjectCreationOrder__c": 1,
        "%vlocity_namespace%__DomainObjectFieldAPIName__c": "OSFMX_KamSendBack__c",
        "%vlocity_namespace%__InterfaceFieldAPIName__c": "OSFMX_KamSendBack__c",
        "%vlocity_namespace%__IsDisabled__c": false,
        "%vlocity_namespace%__IsRequiredForUpsert__c": false,
        "%vlocity_namespace%__MapId__c": "DRPostUpdateQuoteTransportInformationCustom1302",
        "%vlocity_namespace%__UpsertKey__c": false,
        "CurrencyIsoCode": "MXN",
        "Name": "DRPostUpdateQuoteTransportInformation",
        "VlocityDataPackType": "SObject",
        "VlocityRecordSObjectType": "%vlocity_namespace%__DRMapItem__c"
    },
    {
        "%vlocity_namespace%__DomainObjectAPIName__c": "Quote",
        "%vlocity_namespace%__DomainObjectCreationOrder__c": 1,
        "%vlocity_namespace%__DomainObjectFieldAPIName__c": "OSFMX_SubEstatus__c",
        "%vlocity_namespace%__InterfaceFieldAPIName__c": "NuevoSubEstado",
        "%vlocity_namespace%__IsDisabled__c": false,
        "%vlocity_namespace%__IsRequiredForUpsert__c": false,
        "%vlocity_namespace%__MapId__c": "DRPostUpdateQuoteTransportInformationCustom4965",
        "%vlocity_namespace%__UpsertKey__c": false,
        "CurrencyIsoCode": "MXN",
        "Name": "DRPostUpdateQuoteTransportInformation",
        "VlocityDataPackType": "SObject",
        "VlocityRecordSObjectType": "%vlocity_namespace%__DRMapItem__c"
    },
    {
        "%vlocity_namespace%__DomainObjectAPIName__c": "Quote",
        "%vlocity_namespace%__DomainObjectCreationOrder__c": 1,
        "%vlocity_namespace%__DomainObjectFieldAPIName__c": "OSFMX_TransportValidation__c",
        "%vlocity_namespace%__InterfaceFieldAPIName__c": "ValidacionTransporte",
        "%vlocity_namespace%__IsDisabled__c": false,
        "%vlocity_namespace%__IsRequiredForUpsert__c": false,
        "%vlocity_namespace%__MapId__c": "DRPostUpdateQuoteTransportInformationCustom1330",
        "%vlocity_namespace%__UpsertKey__c": false,
        "CurrencyIsoCode": "MXN",
        "Name": "DRPostUpdateQuoteTransportInformation",
        "VlocityDataPackType": "SObject",
        "VlocityRecordSObjectType": "%vlocity_namespace%__DRMapItem__c"
    }
]