{
    "dataSource": {
        "contextVariables": [
            {
                "id": 1,
                "name": "recordId",
                "val": "001c00000386v0CAAQ"
            }
        ],
        "orderBy": {
            "isReverse": false,
            "name": ""
        },
        "type": "IntegrationProcedures",
        "value": {
            "inputMap": {
                "AccountId": "{recordId}"
            },
            "ipMethod": "OSFMX_GetAccountLeffSidebar360VW",
            "resultVar": "[\"AccountLeffSidebar360VW\"]",
            "vlocityAsync": false
        }
    },
    "enableLwc": true,
    "isFlex": true,
    "lwc": {
        "DeveloperName": "cfOSFMXAccountCenterTopSidebarVW360_1_GlobantRRA",
        "Id": "0Rbc0000000DFPgCAO",
        "MasterLabel": "cfOSFMXAccountCenterTopSidebarVW360_1_GlobantRRA",
        "NamespacePrefix": "c"
    },
    "states": [
        {
            "actions": [
            ],
            "blankCardState": false,
            "childCards": [
            ],
            "components": {
                "layer-0": {
                    "children": [
                        {
                            "children": [
                                {
                                    "class": "slds-col ",
                                    "element": "flexIcon",
                                    "elementLabel": "Block-0-Icon-0",
                                    "key": "element_element_block_0_0_flexIcon_0_0",
                                    "name": "Icon",
                                    "parentElementKey": "element_block_0_0",
                                    "property": {
                                        "extraclass": "slds-icon_container slds-icon-action-log-event slds-icon_container--circle",
                                        "iconName": "action:log_event",
                                        "iconType": "Salesforce SVG",
                                        "imgsrc": "",
                                        "record": "{record}",
                                        "size": "medium",
                                        "variant": "inverse"
                                    },
                                    "size": {
                                        "default": "2",
                                        "isResponsive": false
                                    },
                                    "stateIndex": 0,
                                    "styleObject": {
                                        "background": {
                                            "color": "",
                                            "image": "",
                                            "position": "",
                                            "repeat": "",
                                            "size": ""
                                        },
                                        "border": {
                                            "color": "",
                                            "radius": "",
                                            "style": "",
                                            "type": "",
                                            "width": ""
                                        },
                                        "class": "slds-text-align_center ",
                                        "container": {
                                            "class": ""
                                        },
                                        "elementStyleProperties": {
                                        },
                                        "inlineStyle": "",
                                        "margin": [
                                        ],
                                        "padding": [
                                        ],
                                        "size": {
                                            "default": "2",
                                            "isResponsive": false
                                        },
                                        "sizeClass": "slds-size_2-of-12 ",
                                        "style": "             ",
                                        "text": {
                                            "align": "center",
                                            "color": ""
                                        }
                                    },
                                    "type": "element"
                                },
                                {
                                    "class": "slds-col ",
                                    "element": "outputField",
                                    "elementLabel": "Block-0-Text-1",
                                    "key": "element_element_block_0_0_outputField_1_0",
                                    "name": "Text",
                                    "parentElementKey": "element_block_0_0",
                                    "property": {
                                        "card": "{card}",
                                        "mergeField": "%3Cdiv%3E%3Cspan%20style=%22font-size:%2010pt;%22%3E%3Cstrong%3EFecha%20de%20registro:%20%3C/strong%3E%7BFechaRegitro%7D%3C/span%3E%3C/div%3E",
                                        "record": "{record}"
                                    },
                                    "size": {
                                        "default": "9",
                                        "isResponsive": false
                                    },
                                    "stateIndex": 0,
                                    "styleObject": {
                                        "size": {
                                            "default": "9",
                                            "isResponsive": false
                                        },
                                        "sizeClass": "slds-size_9-of-12 "
                                    },
                                    "type": "text"
                                }
                            ],
                            "class": "slds-col ",
                            "element": "block",
                            "elementLabel": "Block-0",
                            "name": "Block",
                            "property": {
                                "card": "{card}",
                                "collapsedByDefault": false,
                                "collapsible": false,
                                "label": "Block",
                                "record": "{record}"
                            },
                            "size": {
                                "default": "6",
                                "isResponsive": false
                            },
                            "stateIndex": 0,
                            "styleObject": {
                                "background": {
                                    "color": "",
                                    "image": "",
                                    "position": "",
                                    "repeat": "",
                                    "size": ""
                                },
                                "border": {
                                    "color": "",
                                    "radius": "",
                                    "style": "",
                                    "type": "",
                                    "width": ""
                                },
                                "class": "slds-p-around_x-small ",
                                "container": {
                                    "class": ""
                                },
                                "elementStyleProperties": {
                                },
                                "inlineStyle": "",
                                "margin": [
                                ],
                                "padding": [
                                    {
                                        "label": "around:x-small",
                                        "size": "x-small",
                                        "type": "around"
                                    }
                                ],
                                "size": {
                                    "default": "6",
                                    "isResponsive": false
                                },
                                "sizeClass": "slds-size_6-of-12 ",
                                "style": "             ",
                                "text": {
                                    "align": "",
                                    "color": ""
                                }
                            },
                            "type": "block"
                        },
                        {
                            "children": [
                                {
                                    "class": "slds-col ",
                                    "element": "flexIcon",
                                    "elementLabel": "Block-0-clone-0-Icon-0",
                                    "key": "element_element_block_1_0_flexIcon_0_0",
                                    "name": "Icon",
                                    "parentElementKey": "element_block_1_0",
                                    "property": {
                                        "extraclass": "slds-icon_container slds-icon-custom-custom32 ",
                                        "iconName": "custom:custom32",
                                        "iconType": "Salesforce SVG",
                                        "imgsrc": "",
                                        "record": "{record}",
                                        "size": "medium",
                                        "variant": "inverse"
                                    },
                                    "size": {
                                        "default": "2",
                                        "isResponsive": false
                                    },
                                    "stateIndex": 0,
                                    "styleObject": {
                                        "background": {
                                            "color": "",
                                            "image": "",
                                            "position": "",
                                            "repeat": "",
                                            "size": ""
                                        },
                                        "border": {
                                            "color": "",
                                            "radius": "",
                                            "style": "",
                                            "type": "",
                                            "width": ""
                                        },
                                        "class": "slds-text-align_center ",
                                        "container": {
                                            "class": ""
                                        },
                                        "elementStyleProperties": {
                                        },
                                        "inlineStyle": "",
                                        "margin": [
                                        ],
                                        "padding": [
                                        ],
                                        "size": {
                                            "default": "2",
                                            "isResponsive": false
                                        },
                                        "sizeClass": "slds-size_2-of-12 ",
                                        "style": "             ",
                                        "text": {
                                            "align": "center",
                                            "color": ""
                                        }
                                    },
                                    "type": "element"
                                },
                                {
                                    "class": "slds-col ",
                                    "element": "outputField",
                                    "elementLabel": "Block-0-clone-0-Text-1",
                                    "key": "element_element_block_1_0_outputField_1_0",
                                    "name": "Text",
                                    "parentElementKey": "element_block_1_0",
                                    "property": {
                                        "card": "{card}",
                                        "mergeField": "%3Cdiv%3E%3Cspan%20style=%22font-size:%2010pt;%22%3E%3Cstrong%3ESector:%20%3C/strong%3E%7BSector%7D%3C/span%3E%3C/div%3E",
                                        "record": "{record}"
                                    },
                                    "size": {
                                        "default": "10",
                                        "isResponsive": false
                                    },
                                    "stateIndex": 0,
                                    "styleObject": {
                                        "size": {
                                            "default": "10",
                                            "isResponsive": false
                                        },
                                        "sizeClass": "slds-size_10-of-12 "
                                    },
                                    "type": "text"
                                }
                            ],
                            "class": "slds-col ",
                            "element": "block",
                            "elementLabel": "Block-0-clone-0",
                            "name": "Block",
                            "property": {
                                "card": "{card}",
                                "collapsedByDefault": false,
                                "collapsible": false,
                                "label": "Block",
                                "record": "{record}"
                            },
                            "size": {
                                "default": "6",
                                "isResponsive": false
                            },
                            "stateIndex": 0,
                            "styleObject": {
                                "background": {
                                    "color": "",
                                    "image": "",
                                    "position": "",
                                    "repeat": "",
                                    "size": ""
                                },
                                "border": {
                                    "color": "",
                                    "radius": "",
                                    "style": "",
                                    "type": "",
                                    "width": ""
                                },
                                "class": "slds-p-around_x-small ",
                                "container": {
                                    "class": ""
                                },
                                "elementStyleProperties": {
                                },
                                "inlineStyle": "",
                                "margin": [
                                ],
                                "padding": [
                                    {
                                        "label": "around:x-small",
                                        "size": "x-small",
                                        "type": "around"
                                    }
                                ],
                                "size": {
                                    "default": "6",
                                    "isResponsive": false
                                },
                                "sizeClass": "slds-size_6-of-12 ",
                                "style": "             ",
                                "text": {
                                    "align": "",
                                    "color": ""
                                }
                            },
                            "type": "block"
                        },
                        {
                            "children": [
                                {
                                    "class": "slds-col ",
                                    "element": "flexIcon",
                                    "elementLabel": "Block-0-clone-0-Icon-0",
                                    "key": "element_element_block_2_0_flexIcon_0_0",
                                    "name": "Icon",
                                    "parentElementKey": "element_block_2_0",
                                    "property": {
                                        "extraclass": "slds-icon_container slds-icon-standard-contact ",
                                        "iconName": "standard:contact",
                                        "iconType": "Salesforce SVG",
                                        "imgsrc": "",
                                        "record": "{record}",
                                        "size": "medium",
                                        "variant": "inverse"
                                    },
                                    "size": {
                                        "default": "2",
                                        "isResponsive": false
                                    },
                                    "stateIndex": 0,
                                    "styleObject": {
                                        "background": {
                                            "color": "",
                                            "image": "",
                                            "position": "",
                                            "repeat": "",
                                            "size": ""
                                        },
                                        "border": {
                                            "color": "",
                                            "radius": "",
                                            "style": "",
                                            "type": "",
                                            "width": ""
                                        },
                                        "class": "slds-text-align_center ",
                                        "container": {
                                            "class": ""
                                        },
                                        "elementStyleProperties": {
                                        },
                                        "inlineStyle": "",
                                        "margin": [
                                        ],
                                        "padding": [
                                        ],
                                        "size": {
                                            "default": "2",
                                            "isResponsive": false
                                        },
                                        "sizeClass": "slds-size_2-of-12 ",
                                        "style": "             ",
                                        "text": {
                                            "align": "center",
                                            "color": ""
                                        }
                                    },
                                    "type": "element"
                                },
                                {
                                    "class": "slds-col ",
                                    "element": "outputField",
                                    "elementLabel": "Block-0-clone-0-Text-1-clone-0",
                                    "key": "element_element_block_2_0_outputField_1_0",
                                    "name": "Text",
                                    "parentElementKey": "element_block_2_0",
                                    "property": {
                                        "card": "{card}",
                                        "mergeField": "%3Cdiv%3E%3Cspan%20style=%22font-size:%2010pt;%22%3E%3Cstrong%3EPropietario:%20%3C/strong%3E%7BPropietario%7D%3C/span%3E%3C/div%3E",
                                        "record": "{record}"
                                    },
                                    "size": {
                                        "default": "9",
                                        "isResponsive": false
                                    },
                                    "stateIndex": 0,
                                    "styleObject": {
                                        "size": {
                                            "default": "9",
                                            "isResponsive": false
                                        },
                                        "sizeClass": "slds-size_9-of-12 "
                                    },
                                    "type": "text"
                                }
                            ],
                            "class": "slds-col ",
                            "element": "block",
                            "elementLabel": "Block-0-clone-0",
                            "name": "Block",
                            "property": {
                                "card": "{card}",
                                "collapsedByDefault": false,
                                "collapsible": false,
                                "label": "Block",
                                "record": "{record}"
                            },
                            "size": {
                                "default": "6",
                                "isResponsive": false
                            },
                            "stateIndex": 0,
                            "styleObject": {
                                "background": {
                                    "color": "",
                                    "image": "",
                                    "position": "",
                                    "repeat": "",
                                    "size": ""
                                },
                                "border": {
                                    "color": "",
                                    "radius": "",
                                    "style": "",
                                    "type": "",
                                    "width": ""
                                },
                                "class": "slds-p-around_x-small ",
                                "container": {
                                    "class": ""
                                },
                                "elementStyleProperties": {
                                },
                                "inlineStyle": "",
                                "margin": [
                                ],
                                "padding": [
                                    {
                                        "label": "around:x-small",
                                        "size": "x-small",
                                        "type": "around"
                                    }
                                ],
                                "size": {
                                    "default": "6",
                                    "isResponsive": false
                                },
                                "sizeClass": "slds-size_6-of-12 ",
                                "style": "             ",
                                "text": {
                                    "align": "",
                                    "color": ""
                                }
                            },
                            "type": "block"
                        },
                        {
                            "children": [
                                {
                                    "class": "slds-col ",
                                    "element": "flexIcon",
                                    "elementLabel": "Block-2-clone-0-Icon-2",
                                    "key": "element_element_block_3_0_flexIcon_0_0",
                                    "name": "Icon",
                                    "parentElementKey": "element_block_3_0",
                                    "property": {
                                        "data-conditions": {
                                            "group": [
                                            ],
                                            "id": "state-condition-object",
                                            "isParent": true
                                        },
                                        "extraclass": "slds-icon_container slds-icon-action-new-opportunity slds-icon_container--circle",
                                        "iconName": "action:new_opportunity",
                                        "iconType": "Salesforce SVG",
                                        "imgsrc": "",
                                        "record": "{record}",
                                        "size": "medium",
                                        "variant": "error"
                                    },
                                    "size": {
                                        "default": "2",
                                        "isResponsive": false
                                    },
                                    "stateIndex": 0,
                                    "styleObject": {
                                        "background": {
                                            "color": "",
                                            "image": "",
                                            "position": "",
                                            "repeat": "",
                                            "size": ""
                                        },
                                        "border": {
                                            "color": "",
                                            "radius": "",
                                            "style": "",
                                            "type": "",
                                            "width": ""
                                        },
                                        "class": "slds-text-align_center ",
                                        "container": {
                                            "class": ""
                                        },
                                        "elementStyleProperties": {
                                        },
                                        "inlineStyle": "",
                                        "margin": [
                                        ],
                                        "padding": [
                                        ],
                                        "size": {
                                            "default": "2",
                                            "isResponsive": false
                                        },
                                        "sizeClass": "slds-size_2-of-12 ",
                                        "style": "             ",
                                        "text": {
                                            "align": "center",
                                            "color": ""
                                        }
                                    },
                                    "type": "element"
                                },
                                {
                                    "class": "slds-col ",
                                    "element": "outputField",
                                    "elementLabel": "Block-2-clone-0-Text-1-clone-0",
                                    "key": "element_element_block_3_0_outputField_1_0",
                                    "name": "Text",
                                    "parentElementKey": "element_block_3_0",
                                    "property": {
                                        "card": "{card}",
                                        "data-conditions": {
                                            "group": [
                                            ],
                                            "id": "state-condition-object",
                                            "isParent": true
                                        },
                                        "mergeField": "%3Cdiv%3E%3Cspan%20style=%22font-size:%2010pt;%22%3E&nbsp;%20%7BCountOpp%7D&nbsp;%3C/span%3E%3C/div%3E",
                                        "record": "{record}"
                                    },
                                    "size": {
                                        "default": "10",
                                        "isResponsive": false
                                    },
                                    "stateIndex": 0,
                                    "styleObject": {
                                        "size": {
                                            "default": "10",
                                            "isResponsive": false
                                        },
                                        "sizeClass": "slds-size_10-of-12 "
                                    },
                                    "type": "text"
                                }
                            ],
                            "class": "slds-col ",
                            "element": "block",
                            "elementLabel": "Block-2-clone-0",
                            "name": "Block",
                            "property": {
                                "card": "{card}",
                                "collapsedByDefault": false,
                                "collapsible": false,
                                "label": "Block",
                                "record": "{record}"
                            },
                            "size": {
                                "default": "6",
                                "isResponsive": false
                            },
                            "stateIndex": 0,
                            "styleObject": {
                                "background": {
                                    "color": "",
                                    "image": "",
                                    "position": "",
                                    "repeat": "",
                                    "size": ""
                                },
                                "border": {
                                    "color": "",
                                    "radius": "",
                                    "style": "",
                                    "type": "",
                                    "width": ""
                                },
                                "class": "slds-p-around_x-small ",
                                "container": {
                                    "class": ""
                                },
                                "elementStyleProperties": {
                                },
                                "inlineStyle": "",
                                "margin": [
                                ],
                                "padding": [
                                    {
                                        "label": "around:x-small",
                                        "size": "x-small",
                                        "type": "around"
                                    }
                                ],
                                "size": {
                                    "default": "6",
                                    "isResponsive": false
                                },
                                "sizeClass": "slds-size_6-of-12 ",
                                "style": "             ",
                                "text": {
                                    "align": "",
                                    "color": ""
                                }
                            },
                            "type": "block"
                        }
                    ]
                }
            },
            "conditions": {
                "group": [
                ],
                "id": "state-condition-object",
                "isParent": true
            },
            "definedActions": {
                "actions": [
                ]
            },
            "fields": [
            ],
            "isSmartAction": false,
            "name": "Active",
            "omniscripts": [
            ],
            "smartAction": {
            },
            "styleObject": {
                "background": {
                    "color": "",
                    "image": "",
                    "position": "",
                    "repeat": "",
                    "size": ""
                },
                "border": {
                    "color": "#cccccc",
                    "radius": "",
                    "style": "",
                    "type": "border_top",
                    "width": "2"
                },
                "class": "slds-card slds-border_top slds-p-around_x-small slds-m-bottom_x-small ",
                "container": {
                    "class": "slds-card"
                },
                "elementStyleProperties": {
                },
                "inlineStyle": "",
                "margin": [
                    {
                        "label": "bottom:x-small",
                        "size": "x-small",
                        "type": "bottom"
                    }
                ],
                "padding": [
                    {
                        "label": "around:x-small",
                        "size": "x-small",
                        "type": "around"
                    }
                ],
                "size": {
                    "default": "12",
                    "isResponsive": false
                },
                "sizeClass": "slds-size_12-of-12 ",
                "style": "     border-color:#cccccc; border-width:2px;       ",
                "text": {
                    "align": "",
                    "color": ""
                }
            }
        }
    ],
    "theme": "slds",
    "title": "OSFMXAccountCenterTopSidebarVW360"
}