[
    {
        "%vlocity_namespace%__DomainObjectAPIName__c": "json",
        "%vlocity_namespace%__DomainObjectCreationOrder__c": 0,
        "%vlocity_namespace%__DomainObjectFieldAPIName__c": "Quote",
        "%vlocity_namespace%__FilterGroup__c": 0,
        "%vlocity_namespace%__FilterOperator__c": "=",
        "%vlocity_namespace%__FilterValue__c": "Id",
        "%vlocity_namespace%__InterfaceFieldAPIName__c": "Id",
        "%vlocity_namespace%__InterfaceObjectLookupOrder__c": 1,
        "%vlocity_namespace%__InterfaceObjectName__c": "Quote",
        "%vlocity_namespace%__IsDisabled__c": false,
        "%vlocity_namespace%__IsRequiredForUpsert__c": false,
        "%vlocity_namespace%__MapId__c": "DRGetQuoteGasDistributionPDFCustom3726",
        "%vlocity_namespace%__UpsertKey__c": false,
        "Name": "DRGetQuoteGasDistributionPDF",
        "VlocityDataPackType": "SObject",
        "VlocityRecordSObjectType": "%vlocity_namespace%__DRMapItem__c"
    },
    {
        "%vlocity_namespace%__DomainObjectAPIName__c": "json",
        "%vlocity_namespace%__DomainObjectCreationOrder__c": 0,
        "%vlocity_namespace%__DomainObjectFieldAPIName__c": "costo",
        "%vlocity_namespace%__FilterGroup__c": 0,
        "%vlocity_namespace%__FilterOperator__c": ">",
        "%vlocity_namespace%__FilterValue__c": "'0'",
        "%vlocity_namespace%__InterfaceFieldAPIName__c": "OSFMX_CostMol__c",
        "%vlocity_namespace%__InterfaceObjectLookupOrder__c": 2,
        "%vlocity_namespace%__InterfaceObjectName__c": "OSFMX_Guarrantie__c",
        "%vlocity_namespace%__IsDisabled__c": false,
        "%vlocity_namespace%__IsRequiredForUpsert__c": false,
        "%vlocity_namespace%__MapId__c": "DRGetQuoteGasDistributionPDFCustom9117",
        "%vlocity_namespace%__UpsertKey__c": false,
        "Name": "DRGetQuoteGasDistributionPDF",
        "VlocityDataPackType": "SObject",
        "VlocityRecordSObjectType": "%vlocity_namespace%__DRMapItem__c"
    },
    {
        "%vlocity_namespace%__DomainObjectAPIName__c": "json",
        "%vlocity_namespace%__DomainObjectCreationOrder__c": 1,
        "%vlocity_namespace%__DomainObjectFieldAPIName__c": "aportacionVoluntaria",
        "%vlocity_namespace%__InterfaceFieldAPIName__c": "Quote:OSFMX_VoluntaryContribution__c",
        "%vlocity_namespace%__IsDisabled__c": false,
        "%vlocity_namespace%__IsRequiredForUpsert__c": false,
        "%vlocity_namespace%__MapId__c": "DRGetQuoteGasDistributionPDFCustom2144",
        "%vlocity_namespace%__UpsertKey__c": false,
        "Name": "DRGetQuoteGasDistributionPDF",
        "VlocityDataPackType": "SObject",
        "VlocityRecordSObjectType": "%vlocity_namespace%__DRMapItem__c"
    },
    {
        "%vlocity_namespace%__DomainObjectAPIName__c": "json",
        "%vlocity_namespace%__DomainObjectCreationOrder__c": 1,
        "%vlocity_namespace%__DomainObjectFieldAPIName__c": "capacidadMaximaDiaria",
        "%vlocity_namespace%__InterfaceFieldAPIName__c": "Quote:OSFMX_Maximumdailycapacity__c",
        "%vlocity_namespace%__IsDisabled__c": false,
        "%vlocity_namespace%__IsRequiredForUpsert__c": false,
        "%vlocity_namespace%__MapId__c": "DRGetQuoteGasDistributionPDFCustom1498",
        "%vlocity_namespace%__UpsertKey__c": false,
        "Name": "DRGetQuoteGasDistributionPDF",
        "VlocityDataPackType": "SObject",
        "VlocityRecordSObjectType": "%vlocity_namespace%__DRMapItem__c"
    },
    {
        "%vlocity_namespace%__DomainObjectAPIName__c": "json",
        "%vlocity_namespace%__DomainObjectCreationOrder__c": 1,
        "%vlocity_namespace%__DomainObjectFieldAPIName__c": "cargoCapacidad",
        "%vlocity_namespace%__InterfaceFieldAPIName__c": "Quote:Cargo_por_Capacidad__c",
        "%vlocity_namespace%__IsDisabled__c": false,
        "%vlocity_namespace%__IsRequiredForUpsert__c": false,
        "%vlocity_namespace%__MapId__c": "DRGetQuoteGasDistributionPDFCustom5492",
        "%vlocity_namespace%__UpsertKey__c": false,
        "Name": "DRGetQuoteGasDistributionPDF",
        "VlocityDataPackType": "SObject",
        "VlocityRecordSObjectType": "%vlocity_namespace%__DRMapItem__c"
    },
    {
        "%vlocity_namespace%__DomainObjectAPIName__c": "json",
        "%vlocity_namespace%__DomainObjectCreationOrder__c": 1,
        "%vlocity_namespace%__DomainObjectFieldAPIName__c": "cargoContactoCuentaNegocio",
        "%vlocity_namespace%__InterfaceFieldAPIName__c": "Quote:Opportunity.OSFMX_Contact__r.Title",
        "%vlocity_namespace%__IsDisabled__c": false,
        "%vlocity_namespace%__IsRequiredForUpsert__c": false,
        "%vlocity_namespace%__MapId__c": "DRGetQuoteGasDistributionPDFCustom367",
        "%vlocity_namespace%__UpsertKey__c": false,
        "Name": "DRGetQuoteGasDistributionPDF",
        "VlocityDataPackType": "SObject",
        "VlocityRecordSObjectType": "%vlocity_namespace%__DRMapItem__c"
    },
    {
        "%vlocity_namespace%__DomainObjectAPIName__c": "json",
        "%vlocity_namespace%__DomainObjectCreationOrder__c": 1,
        "%vlocity_namespace%__DomainObjectFieldAPIName__c": "cargoServicio",
        "%vlocity_namespace%__InterfaceFieldAPIName__c": "Quote:Cargo_por_Servicio__c",
        "%vlocity_namespace%__IsDisabled__c": false,
        "%vlocity_namespace%__IsRequiredForUpsert__c": false,
        "%vlocity_namespace%__MapId__c": "DRGetQuoteGasDistributionPDFCustom609",
        "%vlocity_namespace%__UpsertKey__c": false,
        "Name": "DRGetQuoteGasDistributionPDF",
        "VlocityDataPackType": "SObject",
        "VlocityRecordSObjectType": "%vlocity_namespace%__DRMapItem__c"
    },
    {
        "%vlocity_namespace%__DomainObjectAPIName__c": "json",
        "%vlocity_namespace%__DomainObjectCreationOrder__c": 1,
        "%vlocity_namespace%__DomainObjectFieldAPIName__c": "cargoUso",
        "%vlocity_namespace%__InterfaceFieldAPIName__c": "Quote:Cargo_por_Uso__c",
        "%vlocity_namespace%__IsDisabled__c": false,
        "%vlocity_namespace%__IsRequiredForUpsert__c": false,
        "%vlocity_namespace%__MapId__c": "DRGetQuoteGasDistributionPDFCustom2741",
        "%vlocity_namespace%__UpsertKey__c": false,
        "Name": "DRGetQuoteGasDistributionPDF",
        "VlocityDataPackType": "SObject",
        "VlocityRecordSObjectType": "%vlocity_namespace%__DRMapItem__c"
    },
    {
        "%vlocity_namespace%__DomainObjectAPIName__c": "json",
        "%vlocity_namespace%__DomainObjectCreationOrder__c": 1,
        "%vlocity_namespace%__DomainObjectFieldAPIName__c": "cargoVolumetrico",
        "%vlocity_namespace%__InterfaceFieldAPIName__c": "Quote:Cargo_Volumetrico__c",
        "%vlocity_namespace%__IsDisabled__c": false,
        "%vlocity_namespace%__IsRequiredForUpsert__c": false,
        "%vlocity_namespace%__MapId__c": "DRGetQuoteGasDistributionPDFCustom4129",
        "%vlocity_namespace%__UpsertKey__c": false,
        "Name": "DRGetQuoteGasDistributionPDF",
        "VlocityDataPackType": "SObject",
        "VlocityRecordSObjectType": "%vlocity_namespace%__DRMapItem__c"
    },
    {
        "%vlocity_namespace%__DomainObjectAPIName__c": "json",
        "%vlocity_namespace%__DomainObjectCreationOrder__c": 1,
        "%vlocity_namespace%__DomainObjectFieldAPIName__c": "casetaMedicion",
        "%vlocity_namespace%__InterfaceFieldAPIName__c": "Quote:OSFMX_BoxType__c",
        "%vlocity_namespace%__IsDisabled__c": false,
        "%vlocity_namespace%__IsRequiredForUpsert__c": false,
        "%vlocity_namespace%__MapId__c": "DRGetQuoteGasDistributionPDFCustom9103",
        "%vlocity_namespace%__UpsertKey__c": false,
        "Name": "DRGetQuoteGasDistributionPDF",
        "VlocityDataPackType": "SObject",
        "VlocityRecordSObjectType": "%vlocity_namespace%__DRMapItem__c"
    },
    {
        "%vlocity_namespace%__DomainObjectAPIName__c": "json",
        "%vlocity_namespace%__DomainObjectCreationOrder__c": 1,
        "%vlocity_namespace%__DomainObjectFieldAPIName__c": "ciudadCuentaNegocio",
        "%vlocity_namespace%__InterfaceFieldAPIName__c": "Quote:Account.BillingCity",
        "%vlocity_namespace%__IsDisabled__c": false,
        "%vlocity_namespace%__IsRequiredForUpsert__c": false,
        "%vlocity_namespace%__MapId__c": "DRGetQuoteGasDistributionPDFCustom9194",
        "%vlocity_namespace%__UpsertKey__c": false,
        "Name": "DRGetQuoteGasDistributionPDF",
        "VlocityDataPackType": "SObject",
        "VlocityRecordSObjectType": "%vlocity_namespace%__DRMapItem__c"
    },
    {
        "%vlocity_namespace%__DomainObjectAPIName__c": "json",
        "%vlocity_namespace%__DomainObjectCreationOrder__c": 1,
        "%vlocity_namespace%__DomainObjectFieldAPIName__c": "ciudadCuentaServicio",
        "%vlocity_namespace%__InterfaceFieldAPIName__c": "Quote:%vlocity_namespace%__DefaultServiceAccountId__r.BillingCity",
        "%vlocity_namespace%__IsDisabled__c": false,
        "%vlocity_namespace%__IsRequiredForUpsert__c": false,
        "%vlocity_namespace%__MapId__c": "DRGetQuoteGasDistributionPDFCustom8839",
        "%vlocity_namespace%__UpsertKey__c": false,
        "Name": "DRGetQuoteGasDistributionPDF",
        "VlocityDataPackType": "SObject",
        "VlocityRecordSObjectType": "%vlocity_namespace%__DRMapItem__c"
    },
    {
        "%vlocity_namespace%__DomainObjectAPIName__c": "json",
        "%vlocity_namespace%__DomainObjectCreationOrder__c": 1,
        "%vlocity_namespace%__DomainObjectFieldAPIName__c": "clasificacionTarifaria",
        "%vlocity_namespace%__InterfaceFieldAPIName__c": "Quote:Clasificacion_Tarifaria__c",
        "%vlocity_namespace%__IsDisabled__c": false,
        "%vlocity_namespace%__IsRequiredForUpsert__c": false,
        "%vlocity_namespace%__MapId__c": "DRGetQuoteGasDistributionPDFCustom5224",
        "%vlocity_namespace%__UpsertKey__c": false,
        "Name": "DRGetQuoteGasDistributionPDF",
        "VlocityDataPackType": "SObject",
        "VlocityRecordSObjectType": "%vlocity_namespace%__DRMapItem__c"
    },
    {
        "%vlocity_namespace%__DomainObjectAPIName__c": "json",
        "%vlocity_namespace%__DomainObjectCreationOrder__c": 1,
        "%vlocity_namespace%__DomainObjectFieldAPIName__c": "consumoAnualPrevisto",
        "%vlocity_namespace%__InterfaceFieldAPIName__c": "Quote:OSFMX_GJ__c",
        "%vlocity_namespace%__IsDisabled__c": false,
        "%vlocity_namespace%__IsRequiredForUpsert__c": false,
        "%vlocity_namespace%__MapId__c": "DRGetQuoteGasDistributionPDFCustom7971",
        "%vlocity_namespace%__UpsertKey__c": false,
        "Name": "DRGetQuoteGasDistributionPDF",
        "VlocityDataPackType": "SObject",
        "VlocityRecordSObjectType": "%vlocity_namespace%__DRMapItem__c"
    },
    {
        "%vlocity_namespace%__DomainObjectAPIName__c": "json",
        "%vlocity_namespace%__DomainObjectCreationOrder__c": 1,
        "%vlocity_namespace%__DomainObjectFieldAPIName__c": "consumoPico",
        "%vlocity_namespace%__InterfaceFieldAPIName__c": "Quote:OSFMX_MaxComsuption__c",
        "%vlocity_namespace%__IsDisabled__c": false,
        "%vlocity_namespace%__IsRequiredForUpsert__c": false,
        "%vlocity_namespace%__MapId__c": "DRGetQuoteGasDistributionPDFCustom5559",
        "%vlocity_namespace%__UpsertKey__c": false,
        "Name": "DRGetQuoteGasDistributionPDF",
        "VlocityDataPackType": "SObject",
        "VlocityRecordSObjectType": "%vlocity_namespace%__DRMapItem__c"
    },
    {
        "%vlocity_namespace%__DomainObjectAPIName__c": "json",
        "%vlocity_namespace%__DomainObjectCreationOrder__c": 1,
        "%vlocity_namespace%__DomainObjectFieldAPIName__c": "contactoPrincipalCuentaNegocio",
        "%vlocity_namespace%__InterfaceFieldAPIName__c": "Quote:Opportunity.OSFMX_Contact__r.Name",
        "%vlocity_namespace%__IsDisabled__c": false,
        "%vlocity_namespace%__IsRequiredForUpsert__c": false,
        "%vlocity_namespace%__MapId__c": "DRGetQuoteGasDistributionPDFCustom4802",
        "%vlocity_namespace%__UpsertKey__c": false,
        "Name": "DRGetQuoteGasDistributionPDF",
        "VlocityDataPackType": "SObject",
        "VlocityRecordSObjectType": "%vlocity_namespace%__DRMapItem__c"
    },
    {
        "%vlocity_namespace%__DomainObjectAPIName__c": "json",
        "%vlocity_namespace%__DomainObjectCreationOrder__c": 1,
        "%vlocity_namespace%__DomainObjectFieldAPIName__c": "costoEstandar",
        "%vlocity_namespace%__InterfaceFieldAPIName__c": "Quote:OSFMX_CostStandardConnection__c",
        "%vlocity_namespace%__IsDisabled__c": false,
        "%vlocity_namespace%__IsRequiredForUpsert__c": false,
        "%vlocity_namespace%__MapId__c": "DRGetQuoteGasDistributionPDFCustom1250",
        "%vlocity_namespace%__UpsertKey__c": false,
        "Name": "DRGetQuoteGasDistributionPDF",
        "VlocityDataPackType": "SObject",
        "VlocityRecordSObjectType": "%vlocity_namespace%__DRMapItem__c"
    },
    {
        "%vlocity_namespace%__DomainObjectAPIName__c": "json",
        "%vlocity_namespace%__DomainObjectCreationOrder__c": 1,
        "%vlocity_namespace%__DomainObjectFieldAPIName__c": "costoMoleculaGasTransporte",
        "%vlocity_namespace%__InterfaceFieldAPIName__c": "costo:OSFMX_CostMol__c",
        "%vlocity_namespace%__IsDisabled__c": false,
        "%vlocity_namespace%__IsRequiredForUpsert__c": false,
        "%vlocity_namespace%__MapId__c": "DRGetQuoteGasDistributionPDFCustom6560",
        "%vlocity_namespace%__UpsertKey__c": false,
        "Name": "DRGetQuoteGasDistributionPDF",
        "VlocityDataPackType": "SObject",
        "VlocityRecordSObjectType": "%vlocity_namespace%__DRMapItem__c"
    },
    {
        "%vlocity_namespace%__DomainObjectAPIName__c": "json",
        "%vlocity_namespace%__DomainObjectCreationOrder__c": 1,
        "%vlocity_namespace%__DomainObjectFieldAPIName__c": "costoNoEstandar",
        "%vlocity_namespace%__InterfaceFieldAPIName__c": "Quote:OSFMX_CostNoStandardConnection__c",
        "%vlocity_namespace%__IsDisabled__c": false,
        "%vlocity_namespace%__IsRequiredForUpsert__c": false,
        "%vlocity_namespace%__MapId__c": "DRGetQuoteGasDistributionPDFCustom3658",
        "%vlocity_namespace%__UpsertKey__c": false,
        "Name": "DRGetQuoteGasDistributionPDF",
        "VlocityDataPackType": "SObject",
        "VlocityRecordSObjectType": "%vlocity_namespace%__DRMapItem__c"
    },
    {
        "%vlocity_namespace%__DomainObjectAPIName__c": "json",
        "%vlocity_namespace%__DomainObjectCreationOrder__c": 1,
        "%vlocity_namespace%__DomainObjectFieldAPIName__c": "cpCuentaNegocio",
        "%vlocity_namespace%__InterfaceFieldAPIName__c": "Quote:Account.BillingPostalCode",
        "%vlocity_namespace%__IsDisabled__c": false,
        "%vlocity_namespace%__IsRequiredForUpsert__c": false,
        "%vlocity_namespace%__MapId__c": "DRGetQuoteGasDistributionPDFCustom8988",
        "%vlocity_namespace%__UpsertKey__c": false,
        "Name": "DRGetQuoteGasDistributionPDF",
        "VlocityDataPackType": "SObject",
        "VlocityRecordSObjectType": "%vlocity_namespace%__DRMapItem__c"
    },
    {
        "%vlocity_namespace%__DomainObjectAPIName__c": "json",
        "%vlocity_namespace%__DomainObjectCreationOrder__c": 1,
        "%vlocity_namespace%__DomainObjectFieldAPIName__c": "cpCuentaServicio",
        "%vlocity_namespace%__InterfaceFieldAPIName__c": "Quote:%vlocity_namespace%__DefaultServiceAccountId__r.BillingPostalCode",
        "%vlocity_namespace%__IsDisabled__c": false,
        "%vlocity_namespace%__IsRequiredForUpsert__c": false,
        "%vlocity_namespace%__MapId__c": "DRGetQuoteGasDistributionPDFCustom9308",
        "%vlocity_namespace%__UpsertKey__c": false,
        "Name": "DRGetQuoteGasDistributionPDF",
        "VlocityDataPackType": "SObject",
        "VlocityRecordSObjectType": "%vlocity_namespace%__DRMapItem__c"
    },
    {
        "%vlocity_namespace%__DomainObjectAPIName__c": "json",
        "%vlocity_namespace%__DomainObjectCreationOrder__c": 1,
        "%vlocity_namespace%__DomainObjectFieldAPIName__c": "direccionCuentaNegocio",
        "%vlocity_namespace%__InterfaceFieldAPIName__c": "Quote:Account.BillingStreet",
        "%vlocity_namespace%__IsDisabled__c": false,
        "%vlocity_namespace%__IsRequiredForUpsert__c": false,
        "%vlocity_namespace%__MapId__c": "DRGetQuoteGasDistributionPDFCustom9130",
        "%vlocity_namespace%__UpsertKey__c": false,
        "Name": "DRGetQuoteGasDistributionPDF",
        "VlocityDataPackType": "SObject",
        "VlocityRecordSObjectType": "%vlocity_namespace%__DRMapItem__c"
    },
    {
        "%vlocity_namespace%__DomainObjectAPIName__c": "json",
        "%vlocity_namespace%__DomainObjectCreationOrder__c": 1,
        "%vlocity_namespace%__DomainObjectFieldAPIName__c": "direccionCuentaServicio",
        "%vlocity_namespace%__InterfaceFieldAPIName__c": "Quote:%vlocity_namespace%__DefaultServiceAccountId__r.BillingStreet",
        "%vlocity_namespace%__IsDisabled__c": false,
        "%vlocity_namespace%__IsRequiredForUpsert__c": false,
        "%vlocity_namespace%__MapId__c": "DRGetQuoteGasDistributionPDFCustom7716",
        "%vlocity_namespace%__UpsertKey__c": false,
        "Name": "DRGetQuoteGasDistributionPDF",
        "VlocityDataPackType": "SObject",
        "VlocityRecordSObjectType": "%vlocity_namespace%__DRMapItem__c"
    },
    {
        "%vlocity_namespace%__DomainObjectAPIName__c": "json",
        "%vlocity_namespace%__DomainObjectCreationOrder__c": 1,
        "%vlocity_namespace%__DomainObjectFieldAPIName__c": "distanciaDuctoConexion",
        "%vlocity_namespace%__InterfaceFieldAPIName__c": "Quote:OSFMX_MeterNotStandarConnection__c",
        "%vlocity_namespace%__IsDisabled__c": false,
        "%vlocity_namespace%__IsRequiredForUpsert__c": false,
        "%vlocity_namespace%__MapId__c": "DRGetQuoteGasDistributionPDFCustom5061",
        "%vlocity_namespace%__UpsertKey__c": false,
        "Name": "DRGetQuoteGasDistributionPDF",
        "VlocityDataPackType": "SObject",
        "VlocityRecordSObjectType": "%vlocity_namespace%__DRMapItem__c"
    },
    {
        "%vlocity_namespace%__DomainObjectAPIName__c": "json",
        "%vlocity_namespace%__DomainObjectCreationOrder__c": 1,
        "%vlocity_namespace%__DomainObjectFieldAPIName__c": "distribuidoraTransportista",
        "%vlocity_namespace%__InterfaceFieldAPIName__c": "Quote:OSFMX_DistributorOrCarrier__c",
        "%vlocity_namespace%__IsDisabled__c": false,
        "%vlocity_namespace%__IsRequiredForUpsert__c": false,
        "%vlocity_namespace%__MapId__c": "DRGetQuoteGasDistributionPDFCustom860",
        "%vlocity_namespace%__UpsertKey__c": false,
        "Name": "DRGetQuoteGasDistributionPDF",
        "VlocityDataPackType": "SObject",
        "VlocityRecordSObjectType": "%vlocity_namespace%__DRMapItem__c"
    },
    {
        "%vlocity_namespace%__DomainObjectAPIName__c": "json",
        "%vlocity_namespace%__DomainObjectCreationOrder__c": 1,
        "%vlocity_namespace%__DomainObjectFieldAPIName__c": "estadoCuentaNegocio",
        "%vlocity_namespace%__InterfaceFieldAPIName__c": "Quote:Account.BillingState",
        "%vlocity_namespace%__IsDisabled__c": false,
        "%vlocity_namespace%__IsRequiredForUpsert__c": false,
        "%vlocity_namespace%__MapId__c": "DRGetQuoteGasDistributionPDFCustom868",
        "%vlocity_namespace%__UpsertKey__c": false,
        "Name": "DRGetQuoteGasDistributionPDF",
        "VlocityDataPackType": "SObject",
        "VlocityRecordSObjectType": "%vlocity_namespace%__DRMapItem__c"
    },
    {
        "%vlocity_namespace%__DomainObjectAPIName__c": "json",
        "%vlocity_namespace%__DomainObjectCreationOrder__c": 1,
        "%vlocity_namespace%__DomainObjectFieldAPIName__c": "estadoCuentaServicio",
        "%vlocity_namespace%__InterfaceFieldAPIName__c": "Quote:%vlocity_namespace%__DefaultServiceAccountId__r.BillingState",
        "%vlocity_namespace%__IsDisabled__c": false,
        "%vlocity_namespace%__IsRequiredForUpsert__c": false,
        "%vlocity_namespace%__MapId__c": "DRGetQuoteGasDistributionPDFCustom1598",
        "%vlocity_namespace%__UpsertKey__c": false,
        "Name": "DRGetQuoteGasDistributionPDF",
        "VlocityDataPackType": "SObject",
        "VlocityRecordSObjectType": "%vlocity_namespace%__DRMapItem__c"
    },
    {
        "%vlocity_namespace%__DomainObjectAPIName__c": "json",
        "%vlocity_namespace%__DomainObjectCreationOrder__c": 1,
        "%vlocity_namespace%__DomainObjectFieldAPIName__c": "numeroPagos",
        "%vlocity_namespace%__InterfaceFieldAPIName__c": "Quote:OSFMX_NumberFees__c",
        "%vlocity_namespace%__IsDisabled__c": false,
        "%vlocity_namespace%__IsRequiredForUpsert__c": false,
        "%vlocity_namespace%__MapId__c": "DRGetQuoteGasDistributionPDFCustom6144",
        "%vlocity_namespace%__UpsertKey__c": false,
        "Name": "DRGetQuoteGasDistributionPDF",
        "VlocityDataPackType": "SObject",
        "VlocityRecordSObjectType": "%vlocity_namespace%__DRMapItem__c"
    },
    {
        "%vlocity_namespace%__DomainObjectAPIName__c": "json",
        "%vlocity_namespace%__DomainObjectCreationOrder__c": 1,
        "%vlocity_namespace%__DomainObjectFieldAPIName__c": "presionGarantizada",
        "%vlocity_namespace%__InterfaceFieldAPIName__c": "Quote:OSFMX_PressureMinAssured__c",
        "%vlocity_namespace%__IsDisabled__c": false,
        "%vlocity_namespace%__IsRequiredForUpsert__c": false,
        "%vlocity_namespace%__MapId__c": "DRGetQuoteGasDistributionPDFCustom9101",
        "%vlocity_namespace%__UpsertKey__c": false,
        "Name": "DRGetQuoteGasDistributionPDF",
        "VlocityDataPackType": "SObject",
        "VlocityRecordSObjectType": "%vlocity_namespace%__DRMapItem__c"
    },
    {
        "%vlocity_namespace%__DomainObjectAPIName__c": "json",
        "%vlocity_namespace%__DomainObjectCreationOrder__c": 1,
        "%vlocity_namespace%__DomainObjectFieldAPIName__c": "presionMaximaEntrada",
        "%vlocity_namespace%__InterfaceFieldAPIName__c": "Quote:OSFMX_PressureMaxIncome__c",
        "%vlocity_namespace%__IsDisabled__c": false,
        "%vlocity_namespace%__IsRequiredForUpsert__c": false,
        "%vlocity_namespace%__MapId__c": "DRGetQuoteGasDistributionPDFCustom5660",
        "%vlocity_namespace%__UpsertKey__c": false,
        "Name": "DRGetQuoteGasDistributionPDF",
        "VlocityDataPackType": "SObject",
        "VlocityRecordSObjectType": "%vlocity_namespace%__DRMapItem__c"
    },
    {
        "%vlocity_namespace%__DomainObjectAPIName__c": "json",
        "%vlocity_namespace%__DomainObjectCreationOrder__c": 1,
        "%vlocity_namespace%__DomainObjectFieldAPIName__c": "presionMaximaSalida",
        "%vlocity_namespace%__InterfaceFieldAPIName__c": "Quote:OSFMX_PresssureMaxOutput__c",
        "%vlocity_namespace%__IsDisabled__c": false,
        "%vlocity_namespace%__IsRequiredForUpsert__c": false,
        "%vlocity_namespace%__MapId__c": "DRGetQuoteGasDistributionPDFCustom3082",
        "%vlocity_namespace%__UpsertKey__c": false,
        "Name": "DRGetQuoteGasDistributionPDF",
        "VlocityDataPackType": "SObject",
        "VlocityRecordSObjectType": "%vlocity_namespace%__DRMapItem__c"
    },
    {
        "%vlocity_namespace%__DomainObjectAPIName__c": "json",
        "%vlocity_namespace%__DomainObjectCreationOrder__c": 1,
        "%vlocity_namespace%__DomainObjectFieldAPIName__c": "razonSocialCuentaNegocio",
        "%vlocity_namespace%__InterfaceFieldAPIName__c": "Quote:Account.OSFMX_BusinessName__c",
        "%vlocity_namespace%__IsDisabled__c": false,
        "%vlocity_namespace%__IsRequiredForUpsert__c": false,
        "%vlocity_namespace%__MapId__c": "DRGetQuoteGasDistributionPDFCustom7560",
        "%vlocity_namespace%__UpsertKey__c": false,
        "Name": "DRGetQuoteGasDistributionPDF",
        "VlocityDataPackType": "SObject",
        "VlocityRecordSObjectType": "%vlocity_namespace%__DRMapItem__c"
    },
    {
        "%vlocity_namespace%__DomainObjectAPIName__c": "json",
        "%vlocity_namespace%__DomainObjectCreationOrder__c": 1,
        "%vlocity_namespace%__DomainObjectFieldAPIName__c": "solucion",
        "%vlocity_namespace%__InterfaceFieldAPIName__c": "Quote:OSFMX_Solution__c",
        "%vlocity_namespace%__IsDisabled__c": false,
        "%vlocity_namespace%__IsRequiredForUpsert__c": false,
        "%vlocity_namespace%__MapId__c": "DRGetQuoteGasDistributionPDFCustom7811",
        "%vlocity_namespace%__UpsertKey__c": false,
        "Name": "DRGetQuoteGasDistributionPDF",
        "VlocityDataPackType": "SObject",
        "VlocityRecordSObjectType": "%vlocity_namespace%__DRMapItem__c"
    },
    {
        "%vlocity_namespace%__DomainObjectAPIName__c": "json",
        "%vlocity_namespace%__DomainObjectCreationOrder__c": 1,
        "%vlocity_namespace%__DomainObjectFieldAPIName__c": "tasaInteres",
        "%vlocity_namespace%__InterfaceFieldAPIName__c": "Quote:OSFMX_TaxRate__c",
        "%vlocity_namespace%__IsDisabled__c": false,
        "%vlocity_namespace%__IsRequiredForUpsert__c": false,
        "%vlocity_namespace%__MapId__c": "DRGetQuoteGasDistributionPDFCustom6119",
        "%vlocity_namespace%__UpsertKey__c": false,
        "Name": "DRGetQuoteGasDistributionPDF",
        "VlocityDataPackType": "SObject",
        "VlocityRecordSObjectType": "%vlocity_namespace%__DRMapItem__c"
    },
    {
        "%vlocity_namespace%__DomainObjectAPIName__c": "json",
        "%vlocity_namespace%__DomainObjectCreationOrder__c": 1,
        "%vlocity_namespace%__DomainObjectFieldAPIName__c": "tipoConexion",
        "%vlocity_namespace%__InterfaceFieldAPIName__c": "Quote:OSFMX_ConnectionType__c",
        "%vlocity_namespace%__IsDisabled__c": false,
        "%vlocity_namespace%__IsRequiredForUpsert__c": false,
        "%vlocity_namespace%__MapId__c": "DRGetQuoteGasDistributionPDFCustom37",
        "%vlocity_namespace%__UpsertKey__c": false,
        "Name": "DRGetQuoteGasDistributionPDF",
        "VlocityDataPackType": "SObject",
        "VlocityRecordSObjectType": "%vlocity_namespace%__DRMapItem__c"
    }
]