[
    {
        "%vlocity_namespace%__ActiveFlg__c": true,
        "%vlocity_namespace%__ApplicableToAllRecords__c": false,
        "%vlocity_namespace%__ApplicableToEntity__c": "",
        "%vlocity_namespace%__AttributeCategoryCode__c": "OFFERS_PROMOTIONS",
        "%vlocity_namespace%__AttributeCategoryId__c": {
            "%vlocity_namespace%__Code__c": "OFFERS_PROMOTIONS",
            "VlocityDataPackType": "VlocityMatchingKeyObject",
            "VlocityMatchingRecordSourceKey": "%vlocity_namespace%__AttributeCategory__c/OFFERS_PROMOTIONS",
            "VlocityRecordSObjectType": "%vlocity_namespace%__AttributeCategory__c"
        },
        "%vlocity_namespace%__AttributeCategoryName__c": "Offers and Promotions",
        "%vlocity_namespace%__AttributeGroupType__c": "",
        "%vlocity_namespace%__Code__c": "02e5fed1-cd51-b29c-6bb4-42d636b4425e",
        "%vlocity_namespace%__Configurable__c": true,
        "%vlocity_namespace%__CopyMode__c": "",
        "%vlocity_namespace%__CustomConfigUiTemplate__c": "",
        "%vlocity_namespace%__Description__c": "",
        "%vlocity_namespace%__DesignTime__c": "",
        "%vlocity_namespace%__DisplaySequence__c": 1,
        "%vlocity_namespace%__EditMode__c": "",
        "%vlocity_namespace%__EffectiveFromDate__c": "",
        "%vlocity_namespace%__EffectiveUntilDate__c": "",
        "%vlocity_namespace%__ExcludeFromBasketCache__c": false,
        "%vlocity_namespace%__Filterable__c": true,
        "%vlocity_namespace%__GlobalKey__c": "f6140b74-5e53-28cd-9439-33f53094f1f6",
        "%vlocity_namespace%__HelpText__c": "",
        "%vlocity_namespace%__IsCloneable__c": true,
        "%vlocity_namespace%__IsEncrypted__c": false,
        "%vlocity_namespace%__IsNotAssetizable__c": false,
        "%vlocity_namespace%__IsPrivate__c": false,
        "%vlocity_namespace%__Overridable__c": "",
        "%vlocity_namespace%__OwnerId__c": "",
        "%vlocity_namespace%__PicklistId__c": "",
        "%vlocity_namespace%__RunTime__c": "",
        "%vlocity_namespace%__UniqueNameField__c": "",
        "%vlocity_namespace%__ValueType__c": "Text",
        "%vlocity_namespace%__Value__c": "",
        "%vlocity_namespace%__isDefaultHidden__c": false,
        "Name": "No",
        "VlocityDataPackType": "SObject",
        "VlocityRecordSObjectType": "%vlocity_namespace%__Attribute__c",
        "VlocityRecordSourceKey": "%vlocity_namespace%__Attribute__c/02e5fed1-cd51-b29c-6bb4-42d636b4425e"
    },
    {
        "%vlocity_namespace%__ActiveFlg__c": true,
        "%vlocity_namespace%__ApplicableToAllRecords__c": false,
        "%vlocity_namespace%__ApplicableToEntity__c": "",
        "%vlocity_namespace%__AttributeCategoryCode__c": "OFFERS_PROMOTIONS",
        "%vlocity_namespace%__AttributeCategoryId__c": {
            "%vlocity_namespace%__Code__c": "OFFERS_PROMOTIONS",
            "VlocityDataPackType": "VlocityMatchingKeyObject",
            "VlocityMatchingRecordSourceKey": "%vlocity_namespace%__AttributeCategory__c/OFFERS_PROMOTIONS",
            "VlocityRecordSObjectType": "%vlocity_namespace%__AttributeCategory__c"
        },
        "%vlocity_namespace%__AttributeCategoryName__c": "Offers and Promotions",
        "%vlocity_namespace%__AttributeGroupType__c": "",
        "%vlocity_namespace%__Code__c": "185952d1-73ff-1e05-1900-c4a6fc54d820",
        "%vlocity_namespace%__Configurable__c": true,
        "%vlocity_namespace%__CopyMode__c": "",
        "%vlocity_namespace%__CustomConfigUiTemplate__c": "",
        "%vlocity_namespace%__Description__c": "",
        "%vlocity_namespace%__DesignTime__c": "",
        "%vlocity_namespace%__DisplaySequence__c": 1,
        "%vlocity_namespace%__EditMode__c": "",
        "%vlocity_namespace%__EffectiveFromDate__c": "",
        "%vlocity_namespace%__EffectiveUntilDate__c": "",
        "%vlocity_namespace%__ExcludeFromBasketCache__c": false,
        "%vlocity_namespace%__Filterable__c": true,
        "%vlocity_namespace%__GlobalKey__c": "1320ed3d-1464-175d-31da-63c5f439fd70",
        "%vlocity_namespace%__HelpText__c": "",
        "%vlocity_namespace%__IsCloneable__c": true,
        "%vlocity_namespace%__IsEncrypted__c": false,
        "%vlocity_namespace%__IsNotAssetizable__c": false,
        "%vlocity_namespace%__IsPrivate__c": false,
        "%vlocity_namespace%__Overridable__c": "",
        "%vlocity_namespace%__OwnerId__c": "",
        "%vlocity_namespace%__PicklistId__c": "",
        "%vlocity_namespace%__RunTime__c": "",
        "%vlocity_namespace%__UniqueNameField__c": "",
        "%vlocity_namespace%__ValueType__c": "Text",
        "%vlocity_namespace%__Value__c": "",
        "%vlocity_namespace%__isDefaultHidden__c": false,
        "Name": "Do Not Contact",
        "VlocityDataPackType": "SObject",
        "VlocityRecordSObjectType": "%vlocity_namespace%__Attribute__c",
        "VlocityRecordSourceKey": "%vlocity_namespace%__Attribute__c/185952d1-73ff-1e05-1900-c4a6fc54d820"
    },
    {
        "%vlocity_namespace%__ActiveFlg__c": true,
        "%vlocity_namespace%__ApplicableToAllRecords__c": false,
        "%vlocity_namespace%__ApplicableToEntity__c": "",
        "%vlocity_namespace%__AttributeCategoryCode__c": "OFFERS_PROMOTIONS",
        "%vlocity_namespace%__AttributeCategoryId__c": {
            "%vlocity_namespace%__Code__c": "OFFERS_PROMOTIONS",
            "VlocityDataPackType": "VlocityMatchingKeyObject",
            "VlocityMatchingRecordSourceKey": "%vlocity_namespace%__AttributeCategory__c/OFFERS_PROMOTIONS",
            "VlocityRecordSObjectType": "%vlocity_namespace%__AttributeCategory__c"
        },
        "%vlocity_namespace%__AttributeCategoryName__c": "Offers and Promotions",
        "%vlocity_namespace%__AttributeGroupType__c": "",
        "%vlocity_namespace%__Code__c": "2f696dd9-608f-e494-6c3c-0b546f8b5087",
        "%vlocity_namespace%__Configurable__c": true,
        "%vlocity_namespace%__CopyMode__c": "",
        "%vlocity_namespace%__CustomConfigUiTemplate__c": "",
        "%vlocity_namespace%__Description__c": "",
        "%vlocity_namespace%__DesignTime__c": "",
        "%vlocity_namespace%__DisplaySequence__c": 1,
        "%vlocity_namespace%__EditMode__c": "",
        "%vlocity_namespace%__EffectiveFromDate__c": "",
        "%vlocity_namespace%__EffectiveUntilDate__c": "",
        "%vlocity_namespace%__ExcludeFromBasketCache__c": false,
        "%vlocity_namespace%__Filterable__c": true,
        "%vlocity_namespace%__GlobalKey__c": "9fb4c3bd-a428-bf34-0a1f-9dac9143279c",
        "%vlocity_namespace%__HelpText__c": "",
        "%vlocity_namespace%__IsCloneable__c": true,
        "%vlocity_namespace%__IsEncrypted__c": false,
        "%vlocity_namespace%__IsNotAssetizable__c": false,
        "%vlocity_namespace%__IsPrivate__c": false,
        "%vlocity_namespace%__Overridable__c": "",
        "%vlocity_namespace%__OwnerId__c": "",
        "%vlocity_namespace%__PicklistId__c": "",
        "%vlocity_namespace%__RunTime__c": "",
        "%vlocity_namespace%__UniqueNameField__c": "",
        "%vlocity_namespace%__ValueType__c": "Text",
        "%vlocity_namespace%__Value__c": "",
        "%vlocity_namespace%__isDefaultHidden__c": false,
        "Name": "Phone",
        "VlocityDataPackType": "SObject",
        "VlocityRecordSObjectType": "%vlocity_namespace%__Attribute__c",
        "VlocityRecordSourceKey": "%vlocity_namespace%__Attribute__c/2f696dd9-608f-e494-6c3c-0b546f8b5087"
    },
    {
        "%vlocity_namespace%__ActiveFlg__c": true,
        "%vlocity_namespace%__ApplicableToAllRecords__c": false,
        "%vlocity_namespace%__ApplicableToEntity__c": "",
        "%vlocity_namespace%__AttributeCategoryCode__c": "OFFERS_PROMOTIONS",
        "%vlocity_namespace%__AttributeCategoryId__c": {
            "%vlocity_namespace%__Code__c": "OFFERS_PROMOTIONS",
            "VlocityDataPackType": "VlocityMatchingKeyObject",
            "VlocityMatchingRecordSourceKey": "%vlocity_namespace%__AttributeCategory__c/OFFERS_PROMOTIONS",
            "VlocityRecordSObjectType": "%vlocity_namespace%__AttributeCategory__c"
        },
        "%vlocity_namespace%__AttributeCategoryName__c": "Offers and Promotions",
        "%vlocity_namespace%__AttributeGroupType__c": "",
        "%vlocity_namespace%__Code__c": "3e9f857f-1bd8-0904-c4bd-9565944b70ef",
        "%vlocity_namespace%__Configurable__c": true,
        "%vlocity_namespace%__CopyMode__c": "",
        "%vlocity_namespace%__CustomConfigUiTemplate__c": "",
        "%vlocity_namespace%__Description__c": "",
        "%vlocity_namespace%__DesignTime__c": "",
        "%vlocity_namespace%__DisplaySequence__c": 1,
        "%vlocity_namespace%__EditMode__c": "",
        "%vlocity_namespace%__EffectiveFromDate__c": "",
        "%vlocity_namespace%__EffectiveUntilDate__c": "",
        "%vlocity_namespace%__ExcludeFromBasketCache__c": false,
        "%vlocity_namespace%__Filterable__c": true,
        "%vlocity_namespace%__GlobalKey__c": "e00f58be-f4c0-bf76-536b-6bbf7b3389c2",
        "%vlocity_namespace%__HelpText__c": "",
        "%vlocity_namespace%__IsCloneable__c": true,
        "%vlocity_namespace%__IsEncrypted__c": false,
        "%vlocity_namespace%__IsNotAssetizable__c": false,
        "%vlocity_namespace%__IsPrivate__c": false,
        "%vlocity_namespace%__Overridable__c": "",
        "%vlocity_namespace%__OwnerId__c": "",
        "%vlocity_namespace%__PicklistId__c": "",
        "%vlocity_namespace%__RunTime__c": "",
        "%vlocity_namespace%__UniqueNameField__c": "",
        "%vlocity_namespace%__ValueType__c": "Text",
        "%vlocity_namespace%__Value__c": "",
        "%vlocity_namespace%__isDefaultHidden__c": false,
        "Name": "No",
        "VlocityDataPackType": "SObject",
        "VlocityRecordSObjectType": "%vlocity_namespace%__Attribute__c",
        "VlocityRecordSourceKey": "%vlocity_namespace%__Attribute__c/3e9f857f-1bd8-0904-c4bd-9565944b70ef"
    },
    {
        "%vlocity_namespace%__ActiveFlg__c": true,
        "%vlocity_namespace%__ApplicableToAllRecords__c": false,
        "%vlocity_namespace%__ApplicableToEntity__c": "",
        "%vlocity_namespace%__AttributeCategoryCode__c": "OFFERS_PROMOTIONS",
        "%vlocity_namespace%__AttributeCategoryId__c": {
            "%vlocity_namespace%__Code__c": "OFFERS_PROMOTIONS",
            "VlocityDataPackType": "VlocityMatchingKeyObject",
            "VlocityMatchingRecordSourceKey": "%vlocity_namespace%__AttributeCategory__c/OFFERS_PROMOTIONS",
            "VlocityRecordSObjectType": "%vlocity_namespace%__AttributeCategory__c"
        },
        "%vlocity_namespace%__AttributeCategoryName__c": "Offers and Promotions",
        "%vlocity_namespace%__AttributeGroupType__c": "",
        "%vlocity_namespace%__Code__c": "40a270bf-348d-14ea-24e9-bb42c63c5eef",
        "%vlocity_namespace%__Configurable__c": true,
        "%vlocity_namespace%__CopyMode__c": "",
        "%vlocity_namespace%__CustomConfigUiTemplate__c": "",
        "%vlocity_namespace%__Description__c": "",
        "%vlocity_namespace%__DesignTime__c": "",
        "%vlocity_namespace%__DisplaySequence__c": 1,
        "%vlocity_namespace%__EditMode__c": "",
        "%vlocity_namespace%__EffectiveFromDate__c": "",
        "%vlocity_namespace%__EffectiveUntilDate__c": "",
        "%vlocity_namespace%__ExcludeFromBasketCache__c": false,
        "%vlocity_namespace%__Filterable__c": true,
        "%vlocity_namespace%__GlobalKey__c": "822d0422-1f43-b815-6e77-78d68a36cf9b",
        "%vlocity_namespace%__HelpText__c": "",
        "%vlocity_namespace%__IsCloneable__c": true,
        "%vlocity_namespace%__IsEncrypted__c": false,
        "%vlocity_namespace%__IsNotAssetizable__c": false,
        "%vlocity_namespace%__IsPrivate__c": false,
        "%vlocity_namespace%__Overridable__c": "",
        "%vlocity_namespace%__OwnerId__c": "",
        "%vlocity_namespace%__PicklistId__c": "",
        "%vlocity_namespace%__RunTime__c": "",
        "%vlocity_namespace%__UniqueNameField__c": "",
        "%vlocity_namespace%__ValueType__c": "Text",
        "%vlocity_namespace%__Value__c": "",
        "%vlocity_namespace%__isDefaultHidden__c": false,
        "Name": "No",
        "VlocityDataPackType": "SObject",
        "VlocityRecordSObjectType": "%vlocity_namespace%__Attribute__c",
        "VlocityRecordSourceKey": "%vlocity_namespace%__Attribute__c/40a270bf-348d-14ea-24e9-bb42c63c5eef"
    },
    {
        "%vlocity_namespace%__ActiveFlg__c": true,
        "%vlocity_namespace%__ApplicableToAllRecords__c": false,
        "%vlocity_namespace%__ApplicableToEntity__c": "",
        "%vlocity_namespace%__AttributeCategoryCode__c": "OFFERS_PROMOTIONS",
        "%vlocity_namespace%__AttributeCategoryId__c": {
            "%vlocity_namespace%__Code__c": "OFFERS_PROMOTIONS",
            "VlocityDataPackType": "VlocityMatchingKeyObject",
            "VlocityMatchingRecordSourceKey": "%vlocity_namespace%__AttributeCategory__c/OFFERS_PROMOTIONS",
            "VlocityRecordSObjectType": "%vlocity_namespace%__AttributeCategory__c"
        },
        "%vlocity_namespace%__AttributeCategoryName__c": "Offers and Promotions",
        "%vlocity_namespace%__AttributeGroupType__c": "",
        "%vlocity_namespace%__Code__c": "44a0dbf3-597e-2aa4-1aee-9ecb7a2cefb7",
        "%vlocity_namespace%__Configurable__c": true,
        "%vlocity_namespace%__CopyMode__c": "",
        "%vlocity_namespace%__CustomConfigUiTemplate__c": "",
        "%vlocity_namespace%__Description__c": "",
        "%vlocity_namespace%__DesignTime__c": "",
        "%vlocity_namespace%__DisplaySequence__c": 1,
        "%vlocity_namespace%__EditMode__c": "",
        "%vlocity_namespace%__EffectiveFromDate__c": "",
        "%vlocity_namespace%__EffectiveUntilDate__c": "",
        "%vlocity_namespace%__ExcludeFromBasketCache__c": false,
        "%vlocity_namespace%__Filterable__c": true,
        "%vlocity_namespace%__GlobalKey__c": "05f373be-d86c-6476-c946-2e782d81de0d",
        "%vlocity_namespace%__HelpText__c": "",
        "%vlocity_namespace%__IsCloneable__c": true,
        "%vlocity_namespace%__IsEncrypted__c": false,
        "%vlocity_namespace%__IsNotAssetizable__c": false,
        "%vlocity_namespace%__IsPrivate__c": false,
        "%vlocity_namespace%__Overridable__c": "",
        "%vlocity_namespace%__OwnerId__c": "",
        "%vlocity_namespace%__PicklistId__c": "",
        "%vlocity_namespace%__RunTime__c": "",
        "%vlocity_namespace%__UniqueNameField__c": "",
        "%vlocity_namespace%__ValueType__c": "Text",
        "%vlocity_namespace%__Value__c": "",
        "%vlocity_namespace%__isDefaultHidden__c": false,
        "Name": "Text",
        "VlocityDataPackType": "SObject",
        "VlocityRecordSObjectType": "%vlocity_namespace%__Attribute__c",
        "VlocityRecordSourceKey": "%vlocity_namespace%__Attribute__c/44a0dbf3-597e-2aa4-1aee-9ecb7a2cefb7"
    },
    {
        "%vlocity_namespace%__ActiveFlg__c": true,
        "%vlocity_namespace%__ApplicableToAllRecords__c": false,
        "%vlocity_namespace%__ApplicableToEntity__c": "",
        "%vlocity_namespace%__AttributeCategoryCode__c": "OFFERS_PROMOTIONS",
        "%vlocity_namespace%__AttributeCategoryId__c": {
            "%vlocity_namespace%__Code__c": "OFFERS_PROMOTIONS",
            "VlocityDataPackType": "VlocityMatchingKeyObject",
            "VlocityMatchingRecordSourceKey": "%vlocity_namespace%__AttributeCategory__c/OFFERS_PROMOTIONS",
            "VlocityRecordSObjectType": "%vlocity_namespace%__AttributeCategory__c"
        },
        "%vlocity_namespace%__AttributeCategoryName__c": "Offers and Promotions",
        "%vlocity_namespace%__AttributeGroupType__c": "",
        "%vlocity_namespace%__Code__c": "57258283-c064-ed53-667f-7751540346d2",
        "%vlocity_namespace%__Configurable__c": true,
        "%vlocity_namespace%__CopyMode__c": "",
        "%vlocity_namespace%__CustomConfigUiTemplate__c": "",
        "%vlocity_namespace%__Description__c": "",
        "%vlocity_namespace%__DesignTime__c": "",
        "%vlocity_namespace%__DisplaySequence__c": 1,
        "%vlocity_namespace%__EditMode__c": "",
        "%vlocity_namespace%__EffectiveFromDate__c": "",
        "%vlocity_namespace%__EffectiveUntilDate__c": "",
        "%vlocity_namespace%__ExcludeFromBasketCache__c": false,
        "%vlocity_namespace%__Filterable__c": true,
        "%vlocity_namespace%__GlobalKey__c": "d96659b9-c828-92fd-3e14-147766a40ede",
        "%vlocity_namespace%__HelpText__c": "",
        "%vlocity_namespace%__IsCloneable__c": true,
        "%vlocity_namespace%__IsEncrypted__c": false,
        "%vlocity_namespace%__IsNotAssetizable__c": false,
        "%vlocity_namespace%__IsPrivate__c": false,
        "%vlocity_namespace%__Overridable__c": "",
        "%vlocity_namespace%__OwnerId__c": "",
        "%vlocity_namespace%__PicklistId__c": "",
        "%vlocity_namespace%__RunTime__c": "",
        "%vlocity_namespace%__UniqueNameField__c": "",
        "%vlocity_namespace%__ValueType__c": "Text",
        "%vlocity_namespace%__Value__c": "",
        "%vlocity_namespace%__isDefaultHidden__c": false,
        "Name": "Yes",
        "VlocityDataPackType": "SObject",
        "VlocityRecordSObjectType": "%vlocity_namespace%__Attribute__c",
        "VlocityRecordSourceKey": "%vlocity_namespace%__Attribute__c/57258283-c064-ed53-667f-7751540346d2"
    },
    {
        "%vlocity_namespace%__ActiveFlg__c": true,
        "%vlocity_namespace%__ApplicableToAllRecords__c": false,
        "%vlocity_namespace%__ApplicableToEntity__c": "",
        "%vlocity_namespace%__AttributeCategoryCode__c": "OFFERS_PROMOTIONS",
        "%vlocity_namespace%__AttributeCategoryId__c": {
            "%vlocity_namespace%__Code__c": "OFFERS_PROMOTIONS",
            "VlocityDataPackType": "VlocityMatchingKeyObject",
            "VlocityMatchingRecordSourceKey": "%vlocity_namespace%__AttributeCategory__c/OFFERS_PROMOTIONS",
            "VlocityRecordSObjectType": "%vlocity_namespace%__AttributeCategory__c"
        },
        "%vlocity_namespace%__AttributeCategoryName__c": "Offers and Promotions",
        "%vlocity_namespace%__AttributeGroupType__c": "",
        "%vlocity_namespace%__Code__c": "59c8b465-8319-f13c-fee5-45923f3a0e15",
        "%vlocity_namespace%__Configurable__c": true,
        "%vlocity_namespace%__CopyMode__c": "",
        "%vlocity_namespace%__CustomConfigUiTemplate__c": "",
        "%vlocity_namespace%__Description__c": "",
        "%vlocity_namespace%__DesignTime__c": "",
        "%vlocity_namespace%__DisplaySequence__c": 1,
        "%vlocity_namespace%__EditMode__c": "",
        "%vlocity_namespace%__EffectiveFromDate__c": "",
        "%vlocity_namespace%__EffectiveUntilDate__c": "",
        "%vlocity_namespace%__ExcludeFromBasketCache__c": false,
        "%vlocity_namespace%__Filterable__c": true,
        "%vlocity_namespace%__GlobalKey__c": "1b1bad7c-2b4b-113e-11e0-60cfd1b40442",
        "%vlocity_namespace%__HelpText__c": "",
        "%vlocity_namespace%__IsCloneable__c": true,
        "%vlocity_namespace%__IsEncrypted__c": false,
        "%vlocity_namespace%__IsNotAssetizable__c": false,
        "%vlocity_namespace%__IsPrivate__c": false,
        "%vlocity_namespace%__Overridable__c": "",
        "%vlocity_namespace%__OwnerId__c": "",
        "%vlocity_namespace%__PicklistId__c": "",
        "%vlocity_namespace%__RunTime__c": "",
        "%vlocity_namespace%__UniqueNameField__c": "",
        "%vlocity_namespace%__ValueType__c": "Text",
        "%vlocity_namespace%__Value__c": "",
        "%vlocity_namespace%__isDefaultHidden__c": false,
        "Name": "Do Not Contact",
        "VlocityDataPackType": "SObject",
        "VlocityRecordSObjectType": "%vlocity_namespace%__Attribute__c",
        "VlocityRecordSourceKey": "%vlocity_namespace%__Attribute__c/59c8b465-8319-f13c-fee5-45923f3a0e15"
    },
    {
        "%vlocity_namespace%__ActiveFlg__c": true,
        "%vlocity_namespace%__ApplicableToAllRecords__c": false,
        "%vlocity_namespace%__ApplicableToEntity__c": "",
        "%vlocity_namespace%__AttributeCategoryCode__c": "OFFERS_PROMOTIONS",
        "%vlocity_namespace%__AttributeCategoryId__c": {
            "%vlocity_namespace%__Code__c": "OFFERS_PROMOTIONS",
            "VlocityDataPackType": "VlocityMatchingKeyObject",
            "VlocityMatchingRecordSourceKey": "%vlocity_namespace%__AttributeCategory__c/OFFERS_PROMOTIONS",
            "VlocityRecordSObjectType": "%vlocity_namespace%__AttributeCategory__c"
        },
        "%vlocity_namespace%__AttributeCategoryName__c": "Offers and Promotions",
        "%vlocity_namespace%__AttributeGroupType__c": "",
        "%vlocity_namespace%__Code__c": "6f646809-97b7-b42c-7f7a-39adc8f101a1",
        "%vlocity_namespace%__Configurable__c": true,
        "%vlocity_namespace%__CopyMode__c": "",
        "%vlocity_namespace%__CustomConfigUiTemplate__c": "",
        "%vlocity_namespace%__Description__c": "",
        "%vlocity_namespace%__DesignTime__c": "",
        "%vlocity_namespace%__DisplaySequence__c": 1,
        "%vlocity_namespace%__EditMode__c": "",
        "%vlocity_namespace%__EffectiveFromDate__c": "",
        "%vlocity_namespace%__EffectiveUntilDate__c": "",
        "%vlocity_namespace%__ExcludeFromBasketCache__c": false,
        "%vlocity_namespace%__Filterable__c": true,
        "%vlocity_namespace%__GlobalKey__c": "0d9d3fc9-b794-db6f-cc86-a87a61c95799",
        "%vlocity_namespace%__HelpText__c": "",
        "%vlocity_namespace%__IsCloneable__c": true,
        "%vlocity_namespace%__IsEncrypted__c": false,
        "%vlocity_namespace%__IsNotAssetizable__c": false,
        "%vlocity_namespace%__IsPrivate__c": false,
        "%vlocity_namespace%__Overridable__c": "",
        "%vlocity_namespace%__OwnerId__c": "",
        "%vlocity_namespace%__PicklistId__c": "",
        "%vlocity_namespace%__RunTime__c": "",
        "%vlocity_namespace%__UniqueNameField__c": "",
        "%vlocity_namespace%__ValueType__c": "Text",
        "%vlocity_namespace%__Value__c": "",
        "%vlocity_namespace%__isDefaultHidden__c": false,
        "Name": "Yes",
        "VlocityDataPackType": "SObject",
        "VlocityRecordSObjectType": "%vlocity_namespace%__Attribute__c",
        "VlocityRecordSourceKey": "%vlocity_namespace%__Attribute__c/6f646809-97b7-b42c-7f7a-39adc8f101a1"
    },
    {
        "%vlocity_namespace%__ActiveFlg__c": true,
        "%vlocity_namespace%__ApplicableToAllRecords__c": false,
        "%vlocity_namespace%__ApplicableToEntity__c": "",
        "%vlocity_namespace%__AttributeCategoryCode__c": "OFFERS_PROMOTIONS",
        "%vlocity_namespace%__AttributeCategoryId__c": {
            "%vlocity_namespace%__Code__c": "OFFERS_PROMOTIONS",
            "VlocityDataPackType": "VlocityMatchingKeyObject",
            "VlocityMatchingRecordSourceKey": "%vlocity_namespace%__AttributeCategory__c/OFFERS_PROMOTIONS",
            "VlocityRecordSObjectType": "%vlocity_namespace%__AttributeCategory__c"
        },
        "%vlocity_namespace%__AttributeCategoryName__c": "Offers and Promotions",
        "%vlocity_namespace%__AttributeGroupType__c": "",
        "%vlocity_namespace%__Code__c": "8073ec4e-74b4-90ed-4017-da0b9db368b9",
        "%vlocity_namespace%__Configurable__c": true,
        "%vlocity_namespace%__CopyMode__c": "",
        "%vlocity_namespace%__CustomConfigUiTemplate__c": "",
        "%vlocity_namespace%__Description__c": "",
        "%vlocity_namespace%__DesignTime__c": "",
        "%vlocity_namespace%__DisplaySequence__c": 1,
        "%vlocity_namespace%__EditMode__c": "",
        "%vlocity_namespace%__EffectiveFromDate__c": "",
        "%vlocity_namespace%__EffectiveUntilDate__c": "",
        "%vlocity_namespace%__ExcludeFromBasketCache__c": false,
        "%vlocity_namespace%__Filterable__c": true,
        "%vlocity_namespace%__GlobalKey__c": "231470c0-0e0c-ac67-50cd-fa589422e5a5",
        "%vlocity_namespace%__HelpText__c": "",
        "%vlocity_namespace%__IsCloneable__c": true,
        "%vlocity_namespace%__IsEncrypted__c": false,
        "%vlocity_namespace%__IsNotAssetizable__c": false,
        "%vlocity_namespace%__IsPrivate__c": false,
        "%vlocity_namespace%__Overridable__c": "",
        "%vlocity_namespace%__OwnerId__c": "",
        "%vlocity_namespace%__PicklistId__c": "",
        "%vlocity_namespace%__RunTime__c": "",
        "%vlocity_namespace%__UniqueNameField__c": "",
        "%vlocity_namespace%__ValueType__c": "Text",
        "%vlocity_namespace%__Value__c": "",
        "%vlocity_namespace%__isDefaultHidden__c": false,
        "Name": "No",
        "VlocityDataPackType": "SObject",
        "VlocityRecordSObjectType": "%vlocity_namespace%__Attribute__c",
        "VlocityRecordSourceKey": "%vlocity_namespace%__Attribute__c/8073ec4e-74b4-90ed-4017-da0b9db368b9"
    },
    {
        "%vlocity_namespace%__ActiveFlg__c": true,
        "%vlocity_namespace%__ApplicableToAllRecords__c": false,
        "%vlocity_namespace%__ApplicableToEntity__c": "",
        "%vlocity_namespace%__AttributeCategoryCode__c": "OFFERS_PROMOTIONS",
        "%vlocity_namespace%__AttributeCategoryId__c": {
            "%vlocity_namespace%__Code__c": "OFFERS_PROMOTIONS",
            "VlocityDataPackType": "VlocityMatchingKeyObject",
            "VlocityMatchingRecordSourceKey": "%vlocity_namespace%__AttributeCategory__c/OFFERS_PROMOTIONS",
            "VlocityRecordSObjectType": "%vlocity_namespace%__AttributeCategory__c"
        },
        "%vlocity_namespace%__AttributeCategoryName__c": "Offers and Promotions",
        "%vlocity_namespace%__AttributeGroupType__c": "",
        "%vlocity_namespace%__Code__c": "946c0c02-fc46-fd32-aa3d-cb97d62ca8d4",
        "%vlocity_namespace%__Configurable__c": true,
        "%vlocity_namespace%__CopyMode__c": "",
        "%vlocity_namespace%__CustomConfigUiTemplate__c": "",
        "%vlocity_namespace%__Description__c": "",
        "%vlocity_namespace%__DesignTime__c": "",
        "%vlocity_namespace%__DisplaySequence__c": 1,
        "%vlocity_namespace%__EditMode__c": "",
        "%vlocity_namespace%__EffectiveFromDate__c": "",
        "%vlocity_namespace%__EffectiveUntilDate__c": "",
        "%vlocity_namespace%__ExcludeFromBasketCache__c": false,
        "%vlocity_namespace%__Filterable__c": true,
        "%vlocity_namespace%__GlobalKey__c": "85ad7171-db5f-629b-b4d7-9fa2a1066bcb",
        "%vlocity_namespace%__HelpText__c": "",
        "%vlocity_namespace%__IsCloneable__c": true,
        "%vlocity_namespace%__IsEncrypted__c": false,
        "%vlocity_namespace%__IsNotAssetizable__c": false,
        "%vlocity_namespace%__IsPrivate__c": false,
        "%vlocity_namespace%__Overridable__c": "",
        "%vlocity_namespace%__OwnerId__c": "",
        "%vlocity_namespace%__PicklistId__c": "",
        "%vlocity_namespace%__RunTime__c": "",
        "%vlocity_namespace%__UniqueNameField__c": "",
        "%vlocity_namespace%__ValueType__c": "Text",
        "%vlocity_namespace%__Value__c": "",
        "%vlocity_namespace%__isDefaultHidden__c": false,
        "Name": "Text",
        "VlocityDataPackType": "SObject",
        "VlocityRecordSObjectType": "%vlocity_namespace%__Attribute__c",
        "VlocityRecordSourceKey": "%vlocity_namespace%__Attribute__c/946c0c02-fc46-fd32-aa3d-cb97d62ca8d4"
    },
    {
        "%vlocity_namespace%__ActiveFlg__c": true,
        "%vlocity_namespace%__ApplicableToAllRecords__c": false,
        "%vlocity_namespace%__ApplicableToEntity__c": "",
        "%vlocity_namespace%__AttributeCategoryCode__c": "OFFERS_PROMOTIONS",
        "%vlocity_namespace%__AttributeCategoryId__c": {
            "%vlocity_namespace%__Code__c": "OFFERS_PROMOTIONS",
            "VlocityDataPackType": "VlocityMatchingKeyObject",
            "VlocityMatchingRecordSourceKey": "%vlocity_namespace%__AttributeCategory__c/OFFERS_PROMOTIONS",
            "VlocityRecordSObjectType": "%vlocity_namespace%__AttributeCategory__c"
        },
        "%vlocity_namespace%__AttributeCategoryName__c": "Offers and Promotions",
        "%vlocity_namespace%__AttributeGroupType__c": "",
        "%vlocity_namespace%__Code__c": "94aa6fb2-94c0-e003-5b98-2af704c59067",
        "%vlocity_namespace%__Configurable__c": true,
        "%vlocity_namespace%__CopyMode__c": "",
        "%vlocity_namespace%__CustomConfigUiTemplate__c": "",
        "%vlocity_namespace%__Description__c": "",
        "%vlocity_namespace%__DesignTime__c": "",
        "%vlocity_namespace%__DisplaySequence__c": 1,
        "%vlocity_namespace%__EditMode__c": "",
        "%vlocity_namespace%__EffectiveFromDate__c": "",
        "%vlocity_namespace%__EffectiveUntilDate__c": "",
        "%vlocity_namespace%__ExcludeFromBasketCache__c": false,
        "%vlocity_namespace%__Filterable__c": true,
        "%vlocity_namespace%__GlobalKey__c": "31f87139-60ce-d27b-4111-215bf746ce62",
        "%vlocity_namespace%__HelpText__c": "",
        "%vlocity_namespace%__IsCloneable__c": true,
        "%vlocity_namespace%__IsEncrypted__c": false,
        "%vlocity_namespace%__IsNotAssetizable__c": false,
        "%vlocity_namespace%__IsPrivate__c": false,
        "%vlocity_namespace%__Overridable__c": "",
        "%vlocity_namespace%__OwnerId__c": "",
        "%vlocity_namespace%__PicklistId__c": "",
        "%vlocity_namespace%__RunTime__c": "",
        "%vlocity_namespace%__UniqueNameField__c": "",
        "%vlocity_namespace%__ValueType__c": "Text",
        "%vlocity_namespace%__Value__c": "",
        "%vlocity_namespace%__isDefaultHidden__c": false,
        "Name": "No",
        "VlocityDataPackType": "SObject",
        "VlocityRecordSObjectType": "%vlocity_namespace%__Attribute__c",
        "VlocityRecordSourceKey": "%vlocity_namespace%__Attribute__c/94aa6fb2-94c0-e003-5b98-2af704c59067"
    },
    {
        "%vlocity_namespace%__ActiveFlg__c": true,
        "%vlocity_namespace%__ApplicableToAllRecords__c": false,
        "%vlocity_namespace%__ApplicableToEntity__c": "",
        "%vlocity_namespace%__AttributeCategoryCode__c": "OFFERS_PROMOTIONS",
        "%vlocity_namespace%__AttributeCategoryId__c": {
            "%vlocity_namespace%__Code__c": "OFFERS_PROMOTIONS",
            "VlocityDataPackType": "VlocityMatchingKeyObject",
            "VlocityMatchingRecordSourceKey": "%vlocity_namespace%__AttributeCategory__c/OFFERS_PROMOTIONS",
            "VlocityRecordSObjectType": "%vlocity_namespace%__AttributeCategory__c"
        },
        "%vlocity_namespace%__AttributeCategoryName__c": "Offers and Promotions",
        "%vlocity_namespace%__AttributeGroupType__c": "",
        "%vlocity_namespace%__Code__c": "9dfcf466-bb27-e706-333e-eb08a7d2de8c",
        "%vlocity_namespace%__Configurable__c": true,
        "%vlocity_namespace%__CopyMode__c": "",
        "%vlocity_namespace%__CustomConfigUiTemplate__c": "",
        "%vlocity_namespace%__Description__c": "",
        "%vlocity_namespace%__DesignTime__c": "",
        "%vlocity_namespace%__DisplaySequence__c": 1,
        "%vlocity_namespace%__EditMode__c": "",
        "%vlocity_namespace%__EffectiveFromDate__c": "",
        "%vlocity_namespace%__EffectiveUntilDate__c": "",
        "%vlocity_namespace%__ExcludeFromBasketCache__c": false,
        "%vlocity_namespace%__Filterable__c": true,
        "%vlocity_namespace%__GlobalKey__c": "b7917211-c8e2-6eea-bee6-b347d278a72c",
        "%vlocity_namespace%__HelpText__c": "",
        "%vlocity_namespace%__IsCloneable__c": true,
        "%vlocity_namespace%__IsEncrypted__c": false,
        "%vlocity_namespace%__IsNotAssetizable__c": false,
        "%vlocity_namespace%__IsPrivate__c": false,
        "%vlocity_namespace%__Overridable__c": "",
        "%vlocity_namespace%__OwnerId__c": "",
        "%vlocity_namespace%__PicklistId__c": "",
        "%vlocity_namespace%__RunTime__c": "",
        "%vlocity_namespace%__UniqueNameField__c": "",
        "%vlocity_namespace%__ValueType__c": "Text",
        "%vlocity_namespace%__Value__c": "",
        "%vlocity_namespace%__isDefaultHidden__c": false,
        "Name": "Text",
        "VlocityDataPackType": "SObject",
        "VlocityRecordSObjectType": "%vlocity_namespace%__Attribute__c",
        "VlocityRecordSourceKey": "%vlocity_namespace%__Attribute__c/9dfcf466-bb27-e706-333e-eb08a7d2de8c"
    },
    {
        "%vlocity_namespace%__ActiveFlg__c": true,
        "%vlocity_namespace%__ApplicableToAllRecords__c": false,
        "%vlocity_namespace%__ApplicableToEntity__c": "",
        "%vlocity_namespace%__AttributeCategoryCode__c": "OFFERS_PROMOTIONS",
        "%vlocity_namespace%__AttributeCategoryId__c": {
            "%vlocity_namespace%__Code__c": "OFFERS_PROMOTIONS",
            "VlocityDataPackType": "VlocityMatchingKeyObject",
            "VlocityMatchingRecordSourceKey": "%vlocity_namespace%__AttributeCategory__c/OFFERS_PROMOTIONS",
            "VlocityRecordSObjectType": "%vlocity_namespace%__AttributeCategory__c"
        },
        "%vlocity_namespace%__AttributeCategoryName__c": "Offers and Promotions",
        "%vlocity_namespace%__AttributeGroupType__c": "",
        "%vlocity_namespace%__Code__c": "aaa9aa9d-31ed-9afb-bc88-38fd01b4d065",
        "%vlocity_namespace%__Configurable__c": true,
        "%vlocity_namespace%__CopyMode__c": "",
        "%vlocity_namespace%__CustomConfigUiTemplate__c": "",
        "%vlocity_namespace%__Description__c": "",
        "%vlocity_namespace%__DesignTime__c": "",
        "%vlocity_namespace%__DisplaySequence__c": 1,
        "%vlocity_namespace%__EditMode__c": "",
        "%vlocity_namespace%__EffectiveFromDate__c": "",
        "%vlocity_namespace%__EffectiveUntilDate__c": "",
        "%vlocity_namespace%__ExcludeFromBasketCache__c": false,
        "%vlocity_namespace%__Filterable__c": true,
        "%vlocity_namespace%__GlobalKey__c": "bb21be3f-9266-59e5-9bdd-ea4ec74a8c69",
        "%vlocity_namespace%__HelpText__c": "",
        "%vlocity_namespace%__IsCloneable__c": true,
        "%vlocity_namespace%__IsEncrypted__c": false,
        "%vlocity_namespace%__IsNotAssetizable__c": false,
        "%vlocity_namespace%__IsPrivate__c": false,
        "%vlocity_namespace%__Overridable__c": "",
        "%vlocity_namespace%__OwnerId__c": "",
        "%vlocity_namespace%__PicklistId__c": "",
        "%vlocity_namespace%__RunTime__c": "",
        "%vlocity_namespace%__UniqueNameField__c": "",
        "%vlocity_namespace%__ValueType__c": "Text",
        "%vlocity_namespace%__Value__c": "",
        "%vlocity_namespace%__isDefaultHidden__c": false,
        "Name": "Text",
        "VlocityDataPackType": "SObject",
        "VlocityRecordSObjectType": "%vlocity_namespace%__Attribute__c",
        "VlocityRecordSourceKey": "%vlocity_namespace%__Attribute__c/aaa9aa9d-31ed-9afb-bc88-38fd01b4d065"
    },
    {
        "%vlocity_namespace%__ActiveFlg__c": true,
        "%vlocity_namespace%__ApplicableToAllRecords__c": false,
        "%vlocity_namespace%__ApplicableToEntity__c": "",
        "%vlocity_namespace%__AttributeCategoryCode__c": "OFFERS_PROMOTIONS",
        "%vlocity_namespace%__AttributeCategoryId__c": {
            "%vlocity_namespace%__Code__c": "OFFERS_PROMOTIONS",
            "VlocityDataPackType": "VlocityMatchingKeyObject",
            "VlocityMatchingRecordSourceKey": "%vlocity_namespace%__AttributeCategory__c/OFFERS_PROMOTIONS",
            "VlocityRecordSObjectType": "%vlocity_namespace%__AttributeCategory__c"
        },
        "%vlocity_namespace%__AttributeCategoryName__c": "Offers and Promotions",
        "%vlocity_namespace%__AttributeGroupType__c": "",
        "%vlocity_namespace%__Code__c": "bdabe445-6ef3-b6b1-b3e7-e008a3d0afb4",
        "%vlocity_namespace%__Configurable__c": true,
        "%vlocity_namespace%__CopyMode__c": "",
        "%vlocity_namespace%__CustomConfigUiTemplate__c": "",
        "%vlocity_namespace%__Description__c": "",
        "%vlocity_namespace%__DesignTime__c": "",
        "%vlocity_namespace%__DisplaySequence__c": 1,
        "%vlocity_namespace%__EditMode__c": "",
        "%vlocity_namespace%__EffectiveFromDate__c": "",
        "%vlocity_namespace%__EffectiveUntilDate__c": "",
        "%vlocity_namespace%__ExcludeFromBasketCache__c": false,
        "%vlocity_namespace%__Filterable__c": true,
        "%vlocity_namespace%__GlobalKey__c": "e187631d-6bea-0eb6-30b0-b3b38e1dd959",
        "%vlocity_namespace%__HelpText__c": "",
        "%vlocity_namespace%__IsCloneable__c": true,
        "%vlocity_namespace%__IsEncrypted__c": false,
        "%vlocity_namespace%__IsNotAssetizable__c": false,
        "%vlocity_namespace%__IsPrivate__c": false,
        "%vlocity_namespace%__Overridable__c": "",
        "%vlocity_namespace%__OwnerId__c": "",
        "%vlocity_namespace%__PicklistId__c": "",
        "%vlocity_namespace%__RunTime__c": "",
        "%vlocity_namespace%__UniqueNameField__c": "",
        "%vlocity_namespace%__ValueType__c": "Text",
        "%vlocity_namespace%__Value__c": "",
        "%vlocity_namespace%__isDefaultHidden__c": false,
        "Name": "Do Not Contact",
        "VlocityDataPackType": "SObject",
        "VlocityRecordSObjectType": "%vlocity_namespace%__Attribute__c",
        "VlocityRecordSourceKey": "%vlocity_namespace%__Attribute__c/bdabe445-6ef3-b6b1-b3e7-e008a3d0afb4"
    },
    {
        "%vlocity_namespace%__ActiveFlg__c": true,
        "%vlocity_namespace%__ApplicableToAllRecords__c": false,
        "%vlocity_namespace%__ApplicableToEntity__c": "",
        "%vlocity_namespace%__AttributeCategoryCode__c": "OFFERS_PROMOTIONS",
        "%vlocity_namespace%__AttributeCategoryId__c": {
            "%vlocity_namespace%__Code__c": "OFFERS_PROMOTIONS",
            "VlocityDataPackType": "VlocityMatchingKeyObject",
            "VlocityMatchingRecordSourceKey": "%vlocity_namespace%__AttributeCategory__c/OFFERS_PROMOTIONS",
            "VlocityRecordSObjectType": "%vlocity_namespace%__AttributeCategory__c"
        },
        "%vlocity_namespace%__AttributeCategoryName__c": "Offers and Promotions",
        "%vlocity_namespace%__AttributeGroupType__c": "",
        "%vlocity_namespace%__Code__c": "bf58caa8-beaa-aaff-9cf2-507af23e3e22",
        "%vlocity_namespace%__Configurable__c": true,
        "%vlocity_namespace%__CopyMode__c": "",
        "%vlocity_namespace%__CustomConfigUiTemplate__c": "",
        "%vlocity_namespace%__Description__c": "",
        "%vlocity_namespace%__DesignTime__c": "",
        "%vlocity_namespace%__DisplaySequence__c": 1,
        "%vlocity_namespace%__EditMode__c": "",
        "%vlocity_namespace%__EffectiveFromDate__c": "",
        "%vlocity_namespace%__EffectiveUntilDate__c": "",
        "%vlocity_namespace%__ExcludeFromBasketCache__c": false,
        "%vlocity_namespace%__Filterable__c": true,
        "%vlocity_namespace%__GlobalKey__c": "36804f80-f87a-51c0-386b-b9bf818b936c",
        "%vlocity_namespace%__HelpText__c": "",
        "%vlocity_namespace%__IsCloneable__c": true,
        "%vlocity_namespace%__IsEncrypted__c": false,
        "%vlocity_namespace%__IsNotAssetizable__c": false,
        "%vlocity_namespace%__IsPrivate__c": false,
        "%vlocity_namespace%__Overridable__c": "",
        "%vlocity_namespace%__OwnerId__c": "",
        "%vlocity_namespace%__PicklistId__c": "",
        "%vlocity_namespace%__RunTime__c": "",
        "%vlocity_namespace%__UniqueNameField__c": "",
        "%vlocity_namespace%__ValueType__c": "Text",
        "%vlocity_namespace%__Value__c": "",
        "%vlocity_namespace%__isDefaultHidden__c": false,
        "Name": "Phone",
        "VlocityDataPackType": "SObject",
        "VlocityRecordSObjectType": "%vlocity_namespace%__Attribute__c",
        "VlocityRecordSourceKey": "%vlocity_namespace%__Attribute__c/bf58caa8-beaa-aaff-9cf2-507af23e3e22"
    },
    {
        "%vlocity_namespace%__ActiveFlg__c": true,
        "%vlocity_namespace%__ApplicableToAllRecords__c": false,
        "%vlocity_namespace%__ApplicableToEntity__c": "",
        "%vlocity_namespace%__AttributeCategoryCode__c": "OFFERS_PROMOTIONS",
        "%vlocity_namespace%__AttributeCategoryId__c": {
            "%vlocity_namespace%__Code__c": "OFFERS_PROMOTIONS",
            "VlocityDataPackType": "VlocityMatchingKeyObject",
            "VlocityMatchingRecordSourceKey": "%vlocity_namespace%__AttributeCategory__c/OFFERS_PROMOTIONS",
            "VlocityRecordSObjectType": "%vlocity_namespace%__AttributeCategory__c"
        },
        "%vlocity_namespace%__AttributeCategoryName__c": "Offers and Promotions",
        "%vlocity_namespace%__AttributeGroupType__c": "",
        "%vlocity_namespace%__Code__c": "c7f5a405-c327-c19e-15be-9c417d208f69",
        "%vlocity_namespace%__Configurable__c": true,
        "%vlocity_namespace%__CopyMode__c": "",
        "%vlocity_namespace%__CustomConfigUiTemplate__c": "",
        "%vlocity_namespace%__Description__c": "",
        "%vlocity_namespace%__DesignTime__c": "",
        "%vlocity_namespace%__DisplaySequence__c": 1,
        "%vlocity_namespace%__EditMode__c": "",
        "%vlocity_namespace%__EffectiveFromDate__c": "",
        "%vlocity_namespace%__EffectiveUntilDate__c": "",
        "%vlocity_namespace%__ExcludeFromBasketCache__c": false,
        "%vlocity_namespace%__Filterable__c": true,
        "%vlocity_namespace%__GlobalKey__c": "144164b8-e234-4ab2-4bee-f71e50616228",
        "%vlocity_namespace%__HelpText__c": "",
        "%vlocity_namespace%__IsCloneable__c": true,
        "%vlocity_namespace%__IsEncrypted__c": false,
        "%vlocity_namespace%__IsNotAssetizable__c": false,
        "%vlocity_namespace%__IsPrivate__c": false,
        "%vlocity_namespace%__Overridable__c": "",
        "%vlocity_namespace%__OwnerId__c": "",
        "%vlocity_namespace%__PicklistId__c": "",
        "%vlocity_namespace%__RunTime__c": "",
        "%vlocity_namespace%__UniqueNameField__c": "",
        "%vlocity_namespace%__ValueType__c": "Text",
        "%vlocity_namespace%__Value__c": "",
        "%vlocity_namespace%__isDefaultHidden__c": false,
        "Name": "Email",
        "VlocityDataPackType": "SObject",
        "VlocityRecordSObjectType": "%vlocity_namespace%__Attribute__c",
        "VlocityRecordSourceKey": "%vlocity_namespace%__Attribute__c/c7f5a405-c327-c19e-15be-9c417d208f69"
    },
    {
        "%vlocity_namespace%__ActiveFlg__c": true,
        "%vlocity_namespace%__ApplicableToAllRecords__c": false,
        "%vlocity_namespace%__ApplicableToEntity__c": "",
        "%vlocity_namespace%__AttributeCategoryCode__c": "OFFERS_PROMOTIONS",
        "%vlocity_namespace%__AttributeCategoryId__c": {
            "%vlocity_namespace%__Code__c": "OFFERS_PROMOTIONS",
            "VlocityDataPackType": "VlocityMatchingKeyObject",
            "VlocityMatchingRecordSourceKey": "%vlocity_namespace%__AttributeCategory__c/OFFERS_PROMOTIONS",
            "VlocityRecordSObjectType": "%vlocity_namespace%__AttributeCategory__c"
        },
        "%vlocity_namespace%__AttributeCategoryName__c": "Offers and Promotions",
        "%vlocity_namespace%__AttributeGroupType__c": "",
        "%vlocity_namespace%__Code__c": "c8af2f49-d66d-9b68-a77c-86f02ebe30a6",
        "%vlocity_namespace%__Configurable__c": true,
        "%vlocity_namespace%__CopyMode__c": "",
        "%vlocity_namespace%__CustomConfigUiTemplate__c": "",
        "%vlocity_namespace%__Description__c": "",
        "%vlocity_namespace%__DesignTime__c": "",
        "%vlocity_namespace%__DisplaySequence__c": 1,
        "%vlocity_namespace%__EditMode__c": "",
        "%vlocity_namespace%__EffectiveFromDate__c": "",
        "%vlocity_namespace%__EffectiveUntilDate__c": "",
        "%vlocity_namespace%__ExcludeFromBasketCache__c": false,
        "%vlocity_namespace%__Filterable__c": true,
        "%vlocity_namespace%__GlobalKey__c": "c6d93913-3919-2282-3fe8-c677ed638a0e",
        "%vlocity_namespace%__HelpText__c": "",
        "%vlocity_namespace%__IsCloneable__c": true,
        "%vlocity_namespace%__IsEncrypted__c": false,
        "%vlocity_namespace%__IsNotAssetizable__c": false,
        "%vlocity_namespace%__IsPrivate__c": false,
        "%vlocity_namespace%__Overridable__c": "",
        "%vlocity_namespace%__OwnerId__c": "",
        "%vlocity_namespace%__PicklistId__c": "",
        "%vlocity_namespace%__RunTime__c": "",
        "%vlocity_namespace%__UniqueNameField__c": "",
        "%vlocity_namespace%__ValueType__c": "Text",
        "%vlocity_namespace%__Value__c": "",
        "%vlocity_namespace%__isDefaultHidden__c": false,
        "Name": "Yes",
        "VlocityDataPackType": "SObject",
        "VlocityRecordSObjectType": "%vlocity_namespace%__Attribute__c",
        "VlocityRecordSourceKey": "%vlocity_namespace%__Attribute__c/c8af2f49-d66d-9b68-a77c-86f02ebe30a6"
    },
    {
        "%vlocity_namespace%__ActiveFlg__c": true,
        "%vlocity_namespace%__ApplicableToAllRecords__c": false,
        "%vlocity_namespace%__ApplicableToEntity__c": "",
        "%vlocity_namespace%__AttributeCategoryCode__c": "OFFERS_PROMOTIONS",
        "%vlocity_namespace%__AttributeCategoryId__c": {
            "%vlocity_namespace%__Code__c": "OFFERS_PROMOTIONS",
            "VlocityDataPackType": "VlocityMatchingKeyObject",
            "VlocityMatchingRecordSourceKey": "%vlocity_namespace%__AttributeCategory__c/OFFERS_PROMOTIONS",
            "VlocityRecordSObjectType": "%vlocity_namespace%__AttributeCategory__c"
        },
        "%vlocity_namespace%__AttributeCategoryName__c": "Offers and Promotions",
        "%vlocity_namespace%__AttributeGroupType__c": "",
        "%vlocity_namespace%__Code__c": "e3cf0892-6916-79ee-3c83-f1e8d7cf8ee4",
        "%vlocity_namespace%__Configurable__c": true,
        "%vlocity_namespace%__CopyMode__c": "",
        "%vlocity_namespace%__CustomConfigUiTemplate__c": "",
        "%vlocity_namespace%__Description__c": "",
        "%vlocity_namespace%__DesignTime__c": "",
        "%vlocity_namespace%__DisplaySequence__c": 1,
        "%vlocity_namespace%__EditMode__c": "",
        "%vlocity_namespace%__EffectiveFromDate__c": "",
        "%vlocity_namespace%__EffectiveUntilDate__c": "",
        "%vlocity_namespace%__ExcludeFromBasketCache__c": false,
        "%vlocity_namespace%__Filterable__c": true,
        "%vlocity_namespace%__GlobalKey__c": "30ded723-81b8-6b7a-038d-4651a17b7de3",
        "%vlocity_namespace%__HelpText__c": "",
        "%vlocity_namespace%__IsCloneable__c": true,
        "%vlocity_namespace%__IsEncrypted__c": false,
        "%vlocity_namespace%__IsNotAssetizable__c": false,
        "%vlocity_namespace%__IsPrivate__c": false,
        "%vlocity_namespace%__Overridable__c": "",
        "%vlocity_namespace%__OwnerId__c": "",
        "%vlocity_namespace%__PicklistId__c": "",
        "%vlocity_namespace%__RunTime__c": "",
        "%vlocity_namespace%__UniqueNameField__c": "",
        "%vlocity_namespace%__ValueType__c": "Text",
        "%vlocity_namespace%__Value__c": "",
        "%vlocity_namespace%__isDefaultHidden__c": false,
        "Name": "Do Not Contact",
        "VlocityDataPackType": "SObject",
        "VlocityRecordSObjectType": "%vlocity_namespace%__Attribute__c",
        "VlocityRecordSourceKey": "%vlocity_namespace%__Attribute__c/e3cf0892-6916-79ee-3c83-f1e8d7cf8ee4"
    },
    {
        "%vlocity_namespace%__ActiveFlg__c": true,
        "%vlocity_namespace%__ApplicableToAllRecords__c": false,
        "%vlocity_namespace%__ApplicableToEntity__c": "",
        "%vlocity_namespace%__AttributeCategoryCode__c": "OFFERS_PROMOTIONS",
        "%vlocity_namespace%__AttributeCategoryId__c": {
            "%vlocity_namespace%__Code__c": "OFFERS_PROMOTIONS",
            "VlocityDataPackType": "VlocityMatchingKeyObject",
            "VlocityMatchingRecordSourceKey": "%vlocity_namespace%__AttributeCategory__c/OFFERS_PROMOTIONS",
            "VlocityRecordSObjectType": "%vlocity_namespace%__AttributeCategory__c"
        },
        "%vlocity_namespace%__AttributeCategoryName__c": "Offers and Promotions",
        "%vlocity_namespace%__AttributeGroupType__c": "",
        "%vlocity_namespace%__Code__c": "ed33aa90-f7b5-e4b7-d5ed-ceabaed2a74b",
        "%vlocity_namespace%__Configurable__c": true,
        "%vlocity_namespace%__CopyMode__c": "",
        "%vlocity_namespace%__CustomConfigUiTemplate__c": "",
        "%vlocity_namespace%__Description__c": "",
        "%vlocity_namespace%__DesignTime__c": "",
        "%vlocity_namespace%__DisplaySequence__c": 1,
        "%vlocity_namespace%__EditMode__c": "",
        "%vlocity_namespace%__EffectiveFromDate__c": "",
        "%vlocity_namespace%__EffectiveUntilDate__c": "",
        "%vlocity_namespace%__ExcludeFromBasketCache__c": false,
        "%vlocity_namespace%__Filterable__c": true,
        "%vlocity_namespace%__GlobalKey__c": "27a91474-ac2e-3aad-f7e6-11350917cb12",
        "%vlocity_namespace%__HelpText__c": "",
        "%vlocity_namespace%__IsCloneable__c": true,
        "%vlocity_namespace%__IsEncrypted__c": false,
        "%vlocity_namespace%__IsNotAssetizable__c": false,
        "%vlocity_namespace%__IsPrivate__c": false,
        "%vlocity_namespace%__Overridable__c": "",
        "%vlocity_namespace%__OwnerId__c": "",
        "%vlocity_namespace%__PicklistId__c": "",
        "%vlocity_namespace%__RunTime__c": "",
        "%vlocity_namespace%__UniqueNameField__c": "",
        "%vlocity_namespace%__ValueType__c": "Text",
        "%vlocity_namespace%__Value__c": "",
        "%vlocity_namespace%__isDefaultHidden__c": false,
        "Name": "Email",
        "VlocityDataPackType": "SObject",
        "VlocityRecordSObjectType": "%vlocity_namespace%__Attribute__c",
        "VlocityRecordSourceKey": "%vlocity_namespace%__Attribute__c/ed33aa90-f7b5-e4b7-d5ed-ceabaed2a74b"
    },
    {
        "%vlocity_namespace%__ActiveFlg__c": true,
        "%vlocity_namespace%__ApplicableToAllRecords__c": false,
        "%vlocity_namespace%__ApplicableToEntity__c": "",
        "%vlocity_namespace%__AttributeCategoryCode__c": "OFFERS_PROMOTIONS",
        "%vlocity_namespace%__AttributeCategoryId__c": {
            "%vlocity_namespace%__Code__c": "OFFERS_PROMOTIONS",
            "VlocityDataPackType": "VlocityMatchingKeyObject",
            "VlocityMatchingRecordSourceKey": "%vlocity_namespace%__AttributeCategory__c/OFFERS_PROMOTIONS",
            "VlocityRecordSObjectType": "%vlocity_namespace%__AttributeCategory__c"
        },
        "%vlocity_namespace%__AttributeCategoryName__c": "Offers and Promotions",
        "%vlocity_namespace%__AttributeGroupType__c": "",
        "%vlocity_namespace%__Code__c": "ee668a89-d3d1-47ae-8f7f-119b9f8459e3",
        "%vlocity_namespace%__Configurable__c": true,
        "%vlocity_namespace%__CopyMode__c": "",
        "%vlocity_namespace%__CustomConfigUiTemplate__c": "",
        "%vlocity_namespace%__Description__c": "",
        "%vlocity_namespace%__DesignTime__c": "",
        "%vlocity_namespace%__DisplaySequence__c": 1,
        "%vlocity_namespace%__EditMode__c": "",
        "%vlocity_namespace%__EffectiveFromDate__c": "",
        "%vlocity_namespace%__EffectiveUntilDate__c": "",
        "%vlocity_namespace%__ExcludeFromBasketCache__c": false,
        "%vlocity_namespace%__Filterable__c": true,
        "%vlocity_namespace%__GlobalKey__c": "16038ced-d6f5-9d70-c2c0-7973559e5d62",
        "%vlocity_namespace%__HelpText__c": "",
        "%vlocity_namespace%__IsCloneable__c": true,
        "%vlocity_namespace%__IsEncrypted__c": false,
        "%vlocity_namespace%__IsNotAssetizable__c": false,
        "%vlocity_namespace%__IsPrivate__c": false,
        "%vlocity_namespace%__Overridable__c": "",
        "%vlocity_namespace%__OwnerId__c": "",
        "%vlocity_namespace%__PicklistId__c": "",
        "%vlocity_namespace%__RunTime__c": "",
        "%vlocity_namespace%__UniqueNameField__c": "",
        "%vlocity_namespace%__ValueType__c": "Text",
        "%vlocity_namespace%__Value__c": "",
        "%vlocity_namespace%__isDefaultHidden__c": false,
        "Name": "No",
        "VlocityDataPackType": "SObject",
        "VlocityRecordSObjectType": "%vlocity_namespace%__Attribute__c",
        "VlocityRecordSourceKey": "%vlocity_namespace%__Attribute__c/ee668a89-d3d1-47ae-8f7f-119b9f8459e3"
    },
    {
        "%vlocity_namespace%__ActiveFlg__c": true,
        "%vlocity_namespace%__ApplicableToAllRecords__c": false,
        "%vlocity_namespace%__ApplicableToEntity__c": "",
        "%vlocity_namespace%__AttributeCategoryCode__c": "OFFERS_PROMOTIONS",
        "%vlocity_namespace%__AttributeCategoryId__c": {
            "%vlocity_namespace%__Code__c": "OFFERS_PROMOTIONS",
            "VlocityDataPackType": "VlocityMatchingKeyObject",
            "VlocityMatchingRecordSourceKey": "%vlocity_namespace%__AttributeCategory__c/OFFERS_PROMOTIONS",
            "VlocityRecordSObjectType": "%vlocity_namespace%__AttributeCategory__c"
        },
        "%vlocity_namespace%__AttributeCategoryName__c": "Offers and Promotions",
        "%vlocity_namespace%__AttributeGroupType__c": "",
        "%vlocity_namespace%__Code__c": "f4904f72-b7de-f7d6-6af6-4ccb60048dd8",
        "%vlocity_namespace%__Configurable__c": true,
        "%vlocity_namespace%__CopyMode__c": "",
        "%vlocity_namespace%__CustomConfigUiTemplate__c": "",
        "%vlocity_namespace%__Description__c": "",
        "%vlocity_namespace%__DesignTime__c": "",
        "%vlocity_namespace%__DisplaySequence__c": 1,
        "%vlocity_namespace%__EditMode__c": "",
        "%vlocity_namespace%__EffectiveFromDate__c": "",
        "%vlocity_namespace%__EffectiveUntilDate__c": "",
        "%vlocity_namespace%__ExcludeFromBasketCache__c": false,
        "%vlocity_namespace%__Filterable__c": true,
        "%vlocity_namespace%__GlobalKey__c": "5be37f37-4dc1-d080-9cfb-a182357e669d",
        "%vlocity_namespace%__HelpText__c": "",
        "%vlocity_namespace%__IsCloneable__c": true,
        "%vlocity_namespace%__IsEncrypted__c": false,
        "%vlocity_namespace%__IsNotAssetizable__c": false,
        "%vlocity_namespace%__IsPrivate__c": false,
        "%vlocity_namespace%__Overridable__c": "",
        "%vlocity_namespace%__OwnerId__c": "",
        "%vlocity_namespace%__PicklistId__c": "",
        "%vlocity_namespace%__RunTime__c": "",
        "%vlocity_namespace%__UniqueNameField__c": "",
        "%vlocity_namespace%__ValueType__c": "Text",
        "%vlocity_namespace%__Value__c": "",
        "%vlocity_namespace%__isDefaultHidden__c": false,
        "Name": "Yes",
        "VlocityDataPackType": "SObject",
        "VlocityRecordSObjectType": "%vlocity_namespace%__Attribute__c",
        "VlocityRecordSourceKey": "%vlocity_namespace%__Attribute__c/f4904f72-b7de-f7d6-6af6-4ccb60048dd8"
    },
    {
        "%vlocity_namespace%__ActiveFlg__c": true,
        "%vlocity_namespace%__ApplicableToAllRecords__c": false,
        "%vlocity_namespace%__ApplicableToEntity__c": "",
        "%vlocity_namespace%__AttributeCategoryCode__c": "OFFERS_PROMOTIONS",
        "%vlocity_namespace%__AttributeCategoryId__c": {
            "%vlocity_namespace%__Code__c": "OFFERS_PROMOTIONS",
            "VlocityDataPackType": "VlocityMatchingKeyObject",
            "VlocityMatchingRecordSourceKey": "%vlocity_namespace%__AttributeCategory__c/OFFERS_PROMOTIONS",
            "VlocityRecordSObjectType": "%vlocity_namespace%__AttributeCategory__c"
        },
        "%vlocity_namespace%__AttributeCategoryName__c": "Offers and Promotions",
        "%vlocity_namespace%__AttributeGroupType__c": "",
        "%vlocity_namespace%__Code__c": "f4a7559e-2a03-ca5c-38f6-06f19c4c2099",
        "%vlocity_namespace%__Configurable__c": true,
        "%vlocity_namespace%__CopyMode__c": "",
        "%vlocity_namespace%__CustomConfigUiTemplate__c": "",
        "%vlocity_namespace%__Description__c": "",
        "%vlocity_namespace%__DesignTime__c": "",
        "%vlocity_namespace%__DisplaySequence__c": 1,
        "%vlocity_namespace%__EditMode__c": "",
        "%vlocity_namespace%__EffectiveFromDate__c": "",
        "%vlocity_namespace%__EffectiveUntilDate__c": "",
        "%vlocity_namespace%__ExcludeFromBasketCache__c": false,
        "%vlocity_namespace%__Filterable__c": true,
        "%vlocity_namespace%__GlobalKey__c": "bdf4ba26-b917-d9ef-84bb-955a1061e531",
        "%vlocity_namespace%__HelpText__c": "",
        "%vlocity_namespace%__IsCloneable__c": true,
        "%vlocity_namespace%__IsEncrypted__c": false,
        "%vlocity_namespace%__IsNotAssetizable__c": false,
        "%vlocity_namespace%__IsPrivate__c": false,
        "%vlocity_namespace%__Overridable__c": "",
        "%vlocity_namespace%__OwnerId__c": "",
        "%vlocity_namespace%__PicklistId__c": "",
        "%vlocity_namespace%__RunTime__c": "",
        "%vlocity_namespace%__UniqueNameField__c": "",
        "%vlocity_namespace%__ValueType__c": "Text",
        "%vlocity_namespace%__Value__c": "",
        "%vlocity_namespace%__isDefaultHidden__c": false,
        "Name": "No",
        "VlocityDataPackType": "SObject",
        "VlocityRecordSObjectType": "%vlocity_namespace%__Attribute__c",
        "VlocityRecordSourceKey": "%vlocity_namespace%__Attribute__c/f4a7559e-2a03-ca5c-38f6-06f19c4c2099"
    },
    {
        "%vlocity_namespace%__ActiveFlg__c": true,
        "%vlocity_namespace%__ApplicableToAllRecords__c": false,
        "%vlocity_namespace%__ApplicableToEntity__c": "",
        "%vlocity_namespace%__AttributeCategoryCode__c": "OFFERS_PROMOTIONS",
        "%vlocity_namespace%__AttributeCategoryId__c": {
            "%vlocity_namespace%__Code__c": "OFFERS_PROMOTIONS",
            "VlocityDataPackType": "VlocityMatchingKeyObject",
            "VlocityMatchingRecordSourceKey": "%vlocity_namespace%__AttributeCategory__c/OFFERS_PROMOTIONS",
            "VlocityRecordSObjectType": "%vlocity_namespace%__AttributeCategory__c"
        },
        "%vlocity_namespace%__AttributeCategoryName__c": "Offers and Promotions",
        "%vlocity_namespace%__AttributeGroupType__c": "",
        "%vlocity_namespace%__Code__c": "f4fda154-8c55-cc9e-82da-53720039dd62",
        "%vlocity_namespace%__Configurable__c": true,
        "%vlocity_namespace%__CopyMode__c": "",
        "%vlocity_namespace%__CustomConfigUiTemplate__c": "",
        "%vlocity_namespace%__Description__c": "",
        "%vlocity_namespace%__DesignTime__c": "",
        "%vlocity_namespace%__DisplaySequence__c": 1,
        "%vlocity_namespace%__EditMode__c": "",
        "%vlocity_namespace%__EffectiveFromDate__c": "",
        "%vlocity_namespace%__EffectiveUntilDate__c": "",
        "%vlocity_namespace%__ExcludeFromBasketCache__c": false,
        "%vlocity_namespace%__Filterable__c": true,
        "%vlocity_namespace%__GlobalKey__c": "4cf5001e-5f22-c0fa-0284-5bcd51375e18",
        "%vlocity_namespace%__HelpText__c": "",
        "%vlocity_namespace%__IsCloneable__c": true,
        "%vlocity_namespace%__IsEncrypted__c": false,
        "%vlocity_namespace%__IsNotAssetizable__c": false,
        "%vlocity_namespace%__IsPrivate__c": false,
        "%vlocity_namespace%__Overridable__c": "",
        "%vlocity_namespace%__OwnerId__c": "",
        "%vlocity_namespace%__PicklistId__c": "",
        "%vlocity_namespace%__RunTime__c": "",
        "%vlocity_namespace%__UniqueNameField__c": "",
        "%vlocity_namespace%__ValueType__c": "Text",
        "%vlocity_namespace%__Value__c": "",
        "%vlocity_namespace%__isDefaultHidden__c": false,
        "Name": "No",
        "VlocityDataPackType": "SObject",
        "VlocityRecordSObjectType": "%vlocity_namespace%__Attribute__c",
        "VlocityRecordSourceKey": "%vlocity_namespace%__Attribute__c/f4fda154-8c55-cc9e-82da-53720039dd62"
    }
]